{
  "updated": "2026-04-06T00:20:24.755806Z",
  "data": {
    "US": {
      "ticker": "^GSPC",
      "changes": {
        "1d": 0.11,
        "1w": 3.36,
        "1mo": -3.43,
        "3mo": -4.63,
        "ytd": -4.02,
        "1y": 21.98
      }
    },
    "UK": {
      "ticker": "^FTSE",
      "changes": {
        "1d": 0.69,
        "1w": 4.7,
        "1mo": -3.19,
        "3mo": 4.88,
        "ytd": 4.88,
        "1y": 21.23
      }
    },
    "China": {
      "ticker": "000001.SS",
      "changes": {
        "1d": -1.0,
        "1w": -1.1,
        "1mo": -5.88,
        "3mo": -3.56,
        "ytd": -3.56,
        "1y": 16.1
      }
    },
    "Japan": {
      "ticker": "^N225",
      "changes": {
        "1d": 0.72,
        "1w": 4.78,
        "1mo": -3.81,
        "3mo": 1.88,
        "ytd": 3.22,
        "1y": 71.84
      }
    },
    "Europe": {
      "ticker": "^STOXX50E",
      "changes": {
        "1d": -0.7,
        "1w": 3.4,
        "1mo": -4.91,
        "3mo": -3.9,
        "ytd": -3.9,
        "1y": 7.33
      }
    },
    "Korea": {
      "ticker": "^KS11",
      "changes": {
        "1d": null,
        "1w": 6.43,
        "1mo": -3.72,
        "3mo": 18.82,
        "ytd": 24.77,
        "1y": 130.96
      }
    },
    "Brazil": {
      "ticker": "^BVSP",
      "changes": {
        "1d": 0.05,
        "1w": 3.58,
        "1mo": -0.66,
        "3mo": 17.14,
        "ytd": 17.14,
        "1y": 43.34
      }
    },
    "Turkey": {
      "ticker": "XU100.IS",
      "changes": {
        "1d": -0.88,
        "1w": 2.46,
        "1mo": 0.02,
        "3mo": 10.55,
        "ytd": 12.51,
        "1y": 36.4
      }
    },
    "Israel": {
      "ticker": "TA125.TA",
      "changes": {
        "1d": null,
        "1w": null,
        "1mo": null,
        "3mo": null,
        "ytd": null,
        "1y": null
      }
    },
    "HongKong": {
      "ticker": "^HSI",
      "changes": {
        "1d": -0.7,
        "1w": 0.66,
        "1mo": -3.62,
        "3mo": -4.64,
        "ytd": -4.64,
        "1y": 8.25
      }
    },
    "Taiwan": {
      "ticker": "^TWII",
      "changes": {
        "1d": -1.82,
        "1w": -1.63,
        "1mo": -7.19,
        "3mo": 10.98,
        "ytd": 10.98,
        "1y": 52.93
      }
    },
    "Thailand": {
      "ticker": "^SET.BK",
      "changes": {
        "1d": -0.8,
        "1w": 0.3,
        "1mo": 5.01,
        "3mo": 13.59,
        "ytd": 13.59,
        "1y": 25.15
      }
    }
  }
}