{
  "updated": "2026-05-30T00:04:03.647521Z",
  "data": {
    "US": {
      "ticker": "^GSPC",
      "changes": {
        "1d": 0.22,
        "1w": 1.43,
        "1mo": 5.15,
        "3mo": 10.15,
        "ytd": 10.52,
        "1y": 28.22
      }
    },
    "UK": {
      "ticker": "^FTSE",
      "changes": {
        "1d": null,
        "1w": -0.39,
        "1mo": 2.08,
        "3mo": -3.28,
        "ytd": 4.77,
        "1y": 19.61
      }
    },
    "China": {
      "ticker": "000001.SS",
      "changes": {
        "1d": NaN,
        "1w": NaN,
        "1mo": NaN,
        "3mo": NaN,
        "ytd": NaN,
        "1y": NaN
      }
    },
    "Japan": {
      "ticker": "^N225",
      "changes": {
        "1d": null,
        "1w": -0.71,
        "1mo": 9.12,
        "3mo": 11.43,
        "ytd": 24.81,
        "1y": 68.33
      }
    },
    "Europe": {
      "ticker": "^STOXX50E",
      "changes": {
        "1d": null,
        "1w": 0.59,
        "1mo": 4.1,
        "3mo": 1.14,
        "ytd": 2.22,
        "1y": 12.83
      }
    },
    "Korea": {
      "ticker": "^KS11",
      "changes": {
        "1d": NaN,
        "1w": NaN,
        "1mo": NaN,
        "3mo": NaN,
        "ytd": NaN,
        "1y": NaN
      }
    },
    "Brazil": {
      "ticker": "^BVSP",
      "changes": {
        "1d": -0.73,
        "1w": -2.01,
        "1mo": -5.93,
        "3mo": -8.2,
        "ytd": 8.25,
        "1y": 25.45
      }
    },
    "Turkey": {
      "ticker": "XU100.IS",
      "changes": {
        "1d": null,
        "1w": -1.64,
        "1mo": -4.53,
        "3mo": 2.37,
        "ytd": 18.82,
        "1y": 48.99
      }
    },
    "Israel": {
      "ticker": "TA125.TA",
      "changes": {
        "1d": null,
        "1w": null,
        "1mo": null,
        "3mo": null,
        "ytd": null,
        "1y": null
      }
    },
    "HongKong": {
      "ticker": "^HSI",
      "changes": {
        "1d": null,
        "1w": -2.34,
        "1mo": -4.23,
        "3mo": -4.04,
        "ytd": -5.06,
        "1y": 6.08
      }
    },
    "Taiwan": {
      "ticker": "^TWII",
      "changes": {
        "1d": null,
        "1w": -0.02,
        "1mo": 11.02,
        "3mo": 24.34,
        "ytd": 48.68,
        "1y": 104.41
      }
    },
    "Thailand": {
      "ticker": "^SET.BK",
      "changes": {
        "1d": null,
        "1w": 1.2,
        "1mo": 5.18,
        "3mo": 6.99,
        "ytd": 22.57,
        "1y": 34.79
      }
    }
  }
}