{
  "updated": "2026-05-27T23:56:45.938289Z",
  "data": {
    "US": {
      "AAPL": {
        "name": "Apple Inc.",
        "sector": "Technology",
        "marketCap": 4565564915712,
        "currency": "USD",
        "changes": {
          "1d": 0.82,
          "1w": 2.85,
          "1mo": 14.93,
          "3mo": 17.53,
          "ytd": 14.91,
          "1y": 55.71
        }
      },
      "MSFT": {
        "name": "Microsoft Corporation",
        "sector": "Technology",
        "marketCap": 3065492275200,
        "currency": "USD",
        "changes": {
          "1d": -0.81,
          "1w": -1.78,
          "1mo": -3.65,
          "3mo": 3.77,
          "ytd": -12.36,
          "1y": -9.05
        }
      },
      "NVDA": {
        "name": "NVIDIA Corporation",
        "sector": "Technology",
        "marketCap": 5149384769536,
        "currency": "USD",
        "changes": {
          "1d": -1.05,
          "1w": -4.86,
          "1mo": -0.27,
          "3mo": 16.51,
          "ytd": 12.58,
          "1y": 57.74
        }
      },
      "AMZN": {
        "name": "Amazon.com, Inc.",
        "sector": "Cons. Cyclical",
        "marketCap": 2924320391168,
        "currency": "USD",
        "changes": {
          "1d": 2.47,
          "1w": 2.58,
          "1mo": 4.68,
          "3mo": 30.45,
          "ytd": 20.02,
          "1y": 32.79
        }
      },
      "META": {
        "name": "Meta Platforms, Inc.",
        "sector": "Comm. Services",
        "marketCap": 1612546048000,
        "currency": "USD",
        "changes": {
          "1d": 3.74,
          "1w": 4.99,
          "1mo": -5.38,
          "3mo": -2.72,
          "ytd": -2.25,
          "1y": -0.99
        }
      },
      "GOOGL": {
        "name": "Alphabet Inc.",
        "sector": "Comm. Services",
        "marketCap": 4710847741952,
        "currency": "USD",
        "changes": {
          "1d": -0.01,
          "1w": -0.02,
          "1mo": 11.16,
          "3mo": 26.94,
          "ytd": 23.47,
          "1y": 126.37
        }
      },
      "GOOG": {
        "name": "Alphabet Inc.",
        "sector": "Comm. Services",
        "marketCap": 4662386229248,
        "currency": "USD",
        "changes": {
          "1d": -0.0,
          "1w": -0.02,
          "1mo": 10.74,
          "3mo": 25.7,
          "ytd": 22.13,
          "1y": 122.72
        }
      },
      "BRK-B": {
        "name": "Berkshire Hathaway Inc. New",
        "sector": "Financials",
        "marketCap": 1035117264896,
        "currency": "USD",
        "changes": {
          "1d": -0.77,
          "1w": -0.2,
          "1mo": 0.37,
          "3mo": -0.05,
          "ytd": -3.41,
          "1y": -4.61
        }
      },
      "LLY": {
        "name": "Eli Lilly and Company",
        "sector": "Healthcare",
        "marketCap": 965684625408,
        "currency": "USD",
        "changes": {
          "1d": 1.71,
          "1w": 6.29,
          "1mo": 24.12,
          "3mo": 6.56,
          "ytd": 0.58,
          "1y": 51.6
        }
      },
      "AVGO": {
        "name": "Broadcom Inc.",
        "sector": "Technology",
        "marketCap": 1997367148544,
        "currency": "USD",
        "changes": {
          "1d": -0.04,
          "1w": 0.98,
          "1mo": 5.51,
          "3mo": 32.6,
          "ytd": 21.61,
          "1y": 77.62
        }
      },
      "JPM": {
        "name": "JP Morgan Chase & Co.",
        "sector": "Financials",
        "marketCap": 801924120576,
        "currency": "USD",
        "changes": {
          "1d": -2.43,
          "1w": -0.89,
          "1mo": -3.91,
          "3mo": 1.09,
          "ytd": -7.16,
          "1y": 15.79
        }
      },
      "TSLA": {
        "name": "Tesla, Inc.",
        "sector": "Cons. Cyclical",
        "marketCap": 1653870428160,
        "currency": "USD",
        "changes": {
          "1d": 1.56,
          "1w": 5.54,
          "1mo": 17.11,
          "3mo": 9.18,
          "ytd": 0.52,
          "1y": 23.38
        }
      },
      "UNH": {
        "name": "UnitedHealth Group Incorporated",
        "sector": "Healthcare",
        "marketCap": 348736520192,
        "currency": "USD",
        "changes": {
          "1d": 1.9,
          "1w": 0.19,
          "1mo": 4.7,
          "3mo": 31.22,
          "ytd": 15.04,
          "1y": 32.45
        }
      },
      "V": {
        "name": "Visa Inc.",
        "sector": "Financials",
        "marketCap": 623030239232,
        "currency": "USD",
        "changes": {
          "1d": 0.35,
          "1w": -0.95,
          "1mo": 6.14,
          "3mo": 2.43,
          "ytd": -5.05,
          "1y": -8.21
        }
      },
      "XOM": {
        "name": "Exxon Mobil Corporation",
        "sector": "Energy",
        "marketCap": 613037637632,
        "currency": "USD",
        "changes": {
          "1d": -1.27,
          "1w": -5.36,
          "1mo": -1.1,
          "3mo": -3.45,
          "ytd": 22.21,
          "1y": 49.46
        }
      },
      "MA": {
        "name": "Mastercard Incorporated",
        "sector": "Financials",
        "marketCap": 437409382400,
        "currency": "USD",
        "changes": {
          "1d": 0.41,
          "1w": -0.6,
          "1mo": -2.48,
          "3mo": -4.82,
          "ytd": -11.81,
          "1y": -13.54
        }
      },
      "COST": {
        "name": "Costco Wholesale Corporation",
        "sector": "Cons. Defensive",
        "marketCap": 445289627648,
        "currency": "USD",
        "changes": {
          "1d": 0.08,
          "1w": -6.55,
          "1mo": 1.12,
          "3mo": 0.24,
          "ytd": 17.79,
          "1y": -0.38
        }
      },
      "JNJ": {
        "name": "Johnson & Johnson",
        "sector": "Healthcare",
        "marketCap": 556765151232,
        "currency": "USD",
        "changes": {
          "1d": 0.48,
          "1w": 1.44,
          "1mo": 2.12,
          "3mo": -6.41,
          "ytd": 12.78,
          "1y": NaN
        }
      },
      "PG": {
        "name": "Procter & Gamble Company (The)",
        "sector": "Cons. Defensive",
        "marketCap": 343445078016,
        "currency": "USD",
        "changes": {
          "1d": 3.17,
          "1w": 3.55,
          "1mo": -1.13,
          "3mo": -9.12,
          "ytd": 5.55,
          "1y": -9.34
        }
      },
      "HD": {
        "name": "Home Depot, Inc. (The)",
        "sector": "Cons. Cyclical",
        "marketCap": 316587409408,
        "currency": "USD",
        "changes": {
          "1d": 2.35,
          "1w": 2.34,
          "1mo": -3.41,
          "3mo": -13.71,
          "ytd": -7.47,
          "1y": -11.46
        }
      },
      "NFLX": {
        "name": "Netflix, Inc.",
        "sector": "Comm. Services",
        "marketCap": 367813263360,
        "currency": "USD",
        "changes": {
          "1d": -0.38,
          "1w": -0.84,
          "1mo": -5.33,
          "3mo": -10.03,
          "ytd": -4.0,
          "1y": -27.72
        }
      },
      "BAC": {
        "name": "Bank of America Corporation",
        "sector": "Financials",
        "marketCap": 362635788288,
        "currency": "USD",
        "changes": {
          "1d": -2.11,
          "1w": -0.25,
          "1mo": -2.96,
          "3mo": 3.17,
          "ytd": -8.15,
          "1y": 18.59
        }
      },
      "ABBV": {
        "name": "AbbVie Inc.",
        "sector": "Healthcare",
        "marketCap": 380567158784,
        "currency": "USD",
        "changes": {
          "1d": 1.07,
          "1w": 1.46,
          "1mo": 8.96,
          "3mo": -7.29,
          "ytd": -4.52,
          "1y": 21.48
        }
      },
      "KO": {
        "name": "Coca-Cola Company (The)",
        "sector": "Cons. Defensive",
        "marketCap": 351168626688,
        "currency": "USD",
        "changes": {
          "1d": 1.44,
          "1w": 0.09,
          "1mo": 4.17,
          "3mo": 2.44,
          "ytd": 18.9,
          "1y": 18.04
        }
      },
      "CRM": {
        "name": "Salesforce, Inc.",
        "sector": "Technology",
        "marketCap": 145212719104,
        "currency": "USD",
        "changes": {
          "1d": -0.88,
          "1w": -1.44,
          "1mo": -2.1,
          "3mo": -7.77,
          "ytd": -29.83,
          "1y": -35.21
        }
      },
      "AMD": {
        "name": "Advanced Micro Devices, Inc.",
        "sector": "Technology",
        "marketCap": 808027815936,
        "currency": "USD",
        "changes": {
          "1d": -1.66,
          "1w": 10.72,
          "1mo": 53.32,
          "3mo": 149.49,
          "ytd": 121.75,
          "1y": 339.07
        }
      },
      "WMT": {
        "name": "Walmart Inc.",
        "sector": "Cons. Defensive",
        "marketCap": 944881205248,
        "currency": "USD",
        "changes": {
          "1d": -0.03,
          "1w": -9.41,
          "1mo": -6.92,
          "3mo": -6.37,
          "ytd": 5.54,
          "1y": 22.92
        }
      },
      "MRK": {
        "name": "Merck & Company, Inc.",
        "sector": "Healthcare",
        "marketCap": 296971698176,
        "currency": "USD",
        "changes": {
          "1d": 0.43,
          "1w": 6.41,
          "1mo": 9.28,
          "3mo": -0.23,
          "ytd": 13.79,
          "1y": 63.59
        }
      },
      "CVX": {
        "name": "Chevron Corporation",
        "sector": "Energy",
        "marketCap": 363267391488,
        "currency": "USD",
        "changes": {
          "1d": -1.25,
          "1w": -4.67,
          "1mo": -2.28,
          "3mo": -2.92,
          "ytd": 19.22,
          "1y": 39.71
        }
      },
      "ORCL": {
        "name": "Oracle Corporation",
        "sector": "Technology",
        "marketCap": 549209767936,
        "currency": "USD",
        "changes": {
          "1d": -1.09,
          "1w": 1.49,
          "1mo": 15.06,
          "3mo": 28.39,
          "ytd": -1.83,
          "1y": 17.71
        }
      },
      "PEP": {
        "name": "Pepsico, Inc.",
        "sector": "Cons. Defensive",
        "marketCap": 201951854592,
        "currency": "USD",
        "changes": {
          "1d": 1.41,
          "1w": -1.04,
          "1mo": -5.47,
          "3mo": -10.89,
          "ytd": 4.8,
          "1y": 17.59
        }
      },
      "TMO": {
        "name": "Thermo Fisher Scientific Inc",
        "sector": "Healthcare",
        "marketCap": 169537421312,
        "currency": "USD",
        "changes": {
          "1d": 1.79,
          "1w": 0.98,
          "1mo": -2.98,
          "3mo": -10.21,
          "ytd": -22.93,
          "1y": 13.87
        }
      },
      "ACN": {
        "name": "Accenture plc",
        "sector": "Technology",
        "marketCap": 108538142720,
        "currency": "USD",
        "changes": {
          "1d": -0.36,
          "1w": -1.6,
          "1mo": -0.78,
          "3mo": -13.63,
          "ytd": -31.58,
          "1y": -43.43
        }
      },
      "ADBE": {
        "name": "Adobe Inc.",
        "sector": "Technology",
        "marketCap": 96296607744,
        "currency": "USD",
        "changes": {
          "1d": -0.94,
          "1w": -5.97,
          "1mo": -2.04,
          "3mo": -8.68,
          "ytd": -28.52,
          "1y": -42.21
        }
      },
      "MCD": {
        "name": "McDonald's Corporation",
        "sector": "Cons. Cyclical",
        "marketCap": 199595311104,
        "currency": "USD",
        "changes": {
          "1d": 0.59,
          "1w": 0.23,
          "1mo": -3.92,
          "3mo": -15.63,
          "ytd": -6.85,
          "1y": -8.13
        }
      },
      "QCOM": {
        "name": "QUALCOMM Incorporated",
        "sector": "Technology",
        "marketCap": 246003597312,
        "currency": "USD",
        "changes": {
          "1d": -6.2,
          "1w": 15.25,
          "1mo": 55.6,
          "3mo": 66.56,
          "ytd": 35.8,
          "1y": 61.84
        }
      },
      "CSCO": {
        "name": "Cisco Systems, Inc.",
        "sector": "Technology",
        "marketCap": 471671472128,
        "currency": "USD",
        "changes": {
          "1d": 1.13,
          "1w": 4.65,
          "1mo": 37.77,
          "3mo": 51.5,
          "ytd": 58.23,
          "1y": 93.28
        }
      },
      "IBM": {
        "name": "International Business Machines",
        "sector": "Technology",
        "marketCap": 239858728960,
        "currency": "USD",
        "changes": {
          "1d": 1.8,
          "1w": 13.42,
          "1mo": 10.32,
          "3mo": 7.4,
          "ytd": -11.31,
          "1y": 0.57
        }
      },
      "TXN": {
        "name": "Texas Instruments Incorporated",
        "sector": "Technology",
        "marketCap": 288908967936,
        "currency": "USD",
        "changes": {
          "1d": -2.29,
          "1w": 4.12,
          "1mo": 20.4,
          "3mo": 52.07,
          "ytd": 80.91,
          "1y": 77.22
        }
      },
      "NEE": {
        "name": "NextEra Energy, Inc.",
        "sector": "Utilities",
        "marketCap": 182803316736,
        "currency": "USD",
        "changes": {
          "1d": 0.0,
          "1w": -0.7,
          "1mo": -9.18,
          "3mo": NaN,
          "ytd": 9.04,
          "1y": 34.29
        }
      },
      "PM": {
        "name": "Philip Morris International Inc",
        "sector": "Cons. Defensive",
        "marketCap": 283720056832,
        "currency": "USD",
        "changes": {
          "1d": 0.28,
          "1w": -3.49,
          "1mo": 9.74,
          "3mo": -0.08,
          "ytd": 14.58,
          "1y": 5.43
        }
      },
      "GE": {
        "name": "GE Aerospace",
        "sector": "Industrials",
        "marketCap": 331430395904,
        "currency": "USD",
        "changes": {
          "1d": 0.86,
          "1w": 5.68,
          "1mo": 9.69,
          "3mo": -8.12,
          "ytd": -0.96,
          "1y": 30.87
        }
      },
      "RTX": {
        "name": "RTX Corporation",
        "sector": "Industrials",
        "marketCap": 237810810880,
        "currency": "USD",
        "changes": {
          "1d": -1.33,
          "1w": 1.42,
          "1mo": 0.94,
          "3mo": -16.42,
          "ytd": -4.99,
          "1y": 35.04
        }
      },
      "HON": {
        "name": "Honeywell International Inc.",
        "sector": "Industrials",
        "marketCap": 146722390016,
        "currency": "USD",
        "changes": {
          "1d": -0.07,
          "1w": 6.51,
          "1mo": 9.34,
          "3mo": NaN,
          "ytd": 19.45,
          "1y": 11.77
        }
      },
      "INTC": {
        "name": "Intel Corporation",
        "sector": "Technology",
        "marketCap": 612015996928,
        "currency": "USD",
        "changes": {
          "1d": -1.42,
          "1w": 2.36,
          "1mo": 44.07,
          "3mo": 167.63,
          "ytd": 209.22,
          "1y": 497.79
        }
      },
      "AMGN": {
        "name": "Amgen Inc.",
        "sector": "Healthcare",
        "marketCap": 181374369792,
        "currency": "USD",
        "changes": {
          "1d": 0.04,
          "1w": 1.35,
          "1mo": -0.29,
          "3mo": -12.21,
          "ytd": 4.06,
          "1y": 24.34
        }
      },
      "INTU": {
        "name": "Intuit Inc.",
        "sector": "Technology",
        "marketCap": 84175544320,
        "currency": "USD",
        "changes": {
          "1d": 1.11,
          "1w": -19.85,
          "1mo": -23.14,
          "3mo": -26.34,
          "ytd": -50.87,
          "1y": -58.88
        }
      },
      "UNP": {
        "name": "Union Pacific Corporation",
        "sector": "Industrials",
        "marketCap": 165877547008,
        "currency": "USD",
        "changes": {
          "1d": 3.06,
          "1w": 5.11,
          "1mo": 4.35,
          "3mo": NaN,
          "ytd": 21.1,
          "1y": 28.72
        }
      },
      "LOW": {
        "name": "Lowe's Companies, Inc.",
        "sector": "Cons. Cyclical",
        "marketCap": 121647235072,
        "currency": "USD",
        "changes": {
          "1d": 2.24,
          "1w": -1.9,
          "1mo": -9.77,
          "3mo": -15.28,
          "ytd": -11.35,
          "1y": -1.52
        }
      },
      "MDT": {
        "name": "Medtronic plc.",
        "sector": "Healthcare",
        "marketCap": 97549582336,
        "currency": "USD",
        "changes": {
          "1d": -2.09,
          "1w": -2.78,
          "1mo": -7.23,
          "3mo": -21.92,
          "ytd": -20.25,
          "1y": -3.5
        }
      }
    },
    "UK": {
      "SHEL.L": {
        "name": "SHELL PLC ORD EUR0.07",
        "sector": "Energy",
        "marketCap": 173559070720,
        "currency": "GBp",
        "changes": {
          "1d": NaN,
          "1w": NaN,
          "1mo": NaN,
          "3mo": NaN,
          "ytd": NaN,
          "1y": NaN
        }
      },
      "AZN.L": {
        "name": "ASTRAZENECA PLC ORD SHS $0.25",
        "sector": "Healthcare",
        "marketCap": 217242796032,
        "currency": "GBp",
        "changes": {
          "1d": NaN,
          "1w": NaN,
          "1mo": NaN,
          "3mo": NaN,
          "ytd": NaN,
          "1y": NaN
        }
      },
      "HSBA.L": {
        "name": "HSBC HOLDINGS PLC ORD $0.50 (UK",
        "sector": "Financials",
        "marketCap": 240760815616,
        "currency": "GBp",
        "changes": {
          "1d": NaN,
          "1w": NaN,
          "1mo": NaN,
          "3mo": NaN,
          "ytd": NaN,
          "1y": NaN
        }
      },
      "ULVR.L": {
        "name": "UNILEVER PLC ORD 3.5P",
        "sector": "Cons. Defensive",
        "marketCap": 93939785728,
        "currency": "GBp",
        "changes": {
          "1d": NaN,
          "1w": NaN,
          "1mo": NaN,
          "3mo": NaN,
          "ytd": NaN,
          "1y": NaN
        }
      },
      "BP.L": {
        "name": "BP PLC $0.25",
        "sector": "Energy",
        "marketCap": 79505612800,
        "currency": "GBp",
        "changes": {
          "1d": NaN,
          "1w": NaN,
          "1mo": NaN,
          "3mo": NaN,
          "ytd": NaN,
          "1y": NaN
        }
      },
      "RIO.L": {
        "name": "RIO TINTO PLC ORD 10P",
        "sector": "Materials",
        "marketCap": 128603963392,
        "currency": "GBp",
        "changes": {
          "1d": NaN,
          "1w": NaN,
          "1mo": NaN,
          "3mo": NaN,
          "ytd": NaN,
          "1y": NaN
        }
      },
      "GSK.L": {
        "name": "GSK PLC ORD 31 1/4P",
        "sector": "Healthcare",
        "marketCap": 77839261696,
        "currency": "GBp",
        "changes": {
          "1d": NaN,
          "1w": NaN,
          "1mo": NaN,
          "3mo": NaN,
          "ytd": NaN,
          "1y": NaN
        }
      },
      "DGE.L": {
        "name": "DIAGEO PLC ORD 28 101/108P",
        "sector": "Cons. Defensive",
        "marketCap": 35944259584,
        "currency": "GBp",
        "changes": {
          "1d": NaN,
          "1w": NaN,
          "1mo": NaN,
          "3mo": NaN,
          "ytd": NaN,
          "1y": NaN
        }
      },
      "LSEG.L": {
        "name": "LONDON STOCK EXCHANGE GROUP PLC",
        "sector": "Financials",
        "marketCap": 44799098880,
        "currency": "GBp",
        "changes": {
          "1d": NaN,
          "1w": NaN,
          "1mo": NaN,
          "3mo": NaN,
          "ytd": NaN,
          "1y": NaN
        }
      },
      "NG.L": {
        "name": "NATIONAL GRID PLC ORD 12 204/47",
        "sector": "Utilities",
        "marketCap": 63189442560,
        "currency": "GBp",
        "changes": {
          "1d": NaN,
          "1w": NaN,
          "1mo": NaN,
          "3mo": NaN,
          "ytd": NaN,
          "1y": NaN
        }
      },
      "BARC.L": {
        "name": "BARCLAYS PLC ORD 25P",
        "sector": "Financials",
        "marketCap": 61834469376,
        "currency": "GBp",
        "changes": {
          "1d": NaN,
          "1w": NaN,
          "1mo": NaN,
          "3mo": NaN,
          "ytd": NaN,
          "1y": NaN
        }
      },
      "LLOY.L": {
        "name": "LLOYDS BANKING GROUP PLC ORD 10",
        "sector": "Financials",
        "marketCap": 59295768576,
        "currency": "GBp",
        "changes": {
          "1d": NaN,
          "1w": NaN,
          "1mo": NaN,
          "3mo": NaN,
          "ytd": NaN,
          "1y": NaN
        }
      },
      "CPG.L": {
        "name": "COMPASS GROUP PLC ORD 11 1/20P",
        "sector": "Cons. Cyclical",
        "marketCap": 52709703680,
        "currency": "USD",
        "changes": {
          "1d": NaN,
          "1w": NaN,
          "1mo": NaN,
          "3mo": NaN,
          "ytd": NaN,
          "1y": NaN
        }
      },
      "REL.L": {
        "name": "RELX PLC ORD 14 51/116P",
        "sector": "Industrials",
        "marketCap": 43203403776,
        "currency": "GBp",
        "changes": {
          "1d": NaN,
          "1w": NaN,
          "1mo": NaN,
          "3mo": NaN,
          "ytd": NaN,
          "1y": NaN
        }
      },
      "NWG.L": {
        "name": "NATWEST GROUP PLC ORD 107.69P",
        "sector": "Financials",
        "marketCap": 47750217728,
        "currency": "GBp",
        "changes": {
          "1d": NaN,
          "1w": NaN,
          "1mo": NaN,
          "3mo": NaN,
          "ytd": NaN,
          "1y": NaN
        }
      },
      "PRU.L": {
        "name": "PRUDENTIAL PLC ORD 5P",
        "sector": "Financials",
        "marketCap": 27829899264,
        "currency": "GBp",
        "changes": {
          "1d": NaN,
          "1w": NaN,
          "1mo": NaN,
          "3mo": NaN,
          "ytd": NaN,
          "1y": NaN
        }
      },
      "VOD.L": {
        "name": "VODAFONE GROUP PLC ORD USD0.20 ",
        "sector": "Comm. Services",
        "marketCap": 25593792512,
        "currency": "GBp",
        "changes": {
          "1d": NaN,
          "1w": NaN,
          "1mo": NaN,
          "3mo": NaN,
          "ytd": NaN,
          "1y": NaN
        }
      },
      "AAL.L": {
        "name": "ANGLO AMERICAN PLC ORD USD0.623",
        "sector": "Materials",
        "marketCap": 42323771392,
        "currency": "GBp",
        "changes": {
          "1d": NaN,
          "1w": NaN,
          "1mo": NaN,
          "3mo": NaN,
          "ytd": NaN,
          "1y": NaN
        }
      },
      "ANTO.L": {
        "name": "ANTOFAGASTA PLC ORD 5P",
        "sector": "Materials",
        "marketCap": 40351117312,
        "currency": "GBp",
        "changes": {
          "1d": NaN,
          "1w": NaN,
          "1mo": NaN,
          "3mo": NaN,
          "ytd": NaN,
          "1y": NaN
        }
      },
      "WPP.L": {
        "name": "WPP PLC ORD 10P",
        "sector": "Comm. Services",
        "marketCap": 2979963136,
        "currency": "GBp",
        "changes": {
          "1d": NaN,
          "1w": NaN,
          "1mo": NaN,
          "3mo": NaN,
          "ytd": NaN,
          "1y": NaN
        }
      },
      "IMB.L": {
        "name": "IMPERIAL BRANDS PLC ORD 10P",
        "sector": "Cons. Defensive",
        "marketCap": 21593870336,
        "currency": "GBp",
        "changes": {
          "1d": NaN,
          "1w": NaN,
          "1mo": NaN,
          "3mo": NaN,
          "ytd": NaN,
          "1y": NaN
        }
      },
      "ABF.L": {
        "name": "ASSOCIATED BRITISH FOODS PLC OR",
        "sector": "Cons. Defensive",
        "marketCap": 13115387904,
        "currency": "GBp",
        "changes": {
          "1d": NaN,
          "1w": NaN,
          "1mo": NaN,
          "3mo": NaN,
          "ytd": NaN,
          "1y": NaN
        }
      },
      "BATS.L": {
        "name": "BRITISH AMERICAN TOBACCO PLC OR",
        "sector": "Cons. Defensive",
        "marketCap": 103216513024,
        "currency": "GBp",
        "changes": {
          "1d": NaN,
          "1w": NaN,
          "1mo": NaN,
          "3mo": NaN,
          "ytd": NaN,
          "1y": NaN
        }
      },
      "BT-A.L": {
        "name": "BT GROUP PLC ORD 5P",
        "sector": "Comm. Services",
        "marketCap": 21137516544,
        "currency": "GBp",
        "changes": {
          "1d": NaN,
          "1w": NaN,
          "1mo": NaN,
          "3mo": NaN,
          "ytd": NaN,
          "1y": NaN
        }
      },
      "EXPN.L": {
        "name": "EXPERIAN PLC ORD USD0.10",
        "sector": "Industrials",
        "marketCap": 23060815872,
        "currency": "GBp",
        "changes": {
          "1d": NaN,
          "1w": NaN,
          "1mo": NaN,
          "3mo": NaN,
          "ytd": NaN,
          "1y": NaN
        }
      },
      "LAND.L": {
        "name": "LAND SECURITIES GROUP PLC ORD 1",
        "sector": "Real Estate",
        "marketCap": 4753368576,
        "currency": "GBp",
        "changes": {
          "1d": NaN,
          "1w": NaN,
          "1mo": NaN,
          "3mo": NaN,
          "ytd": NaN,
          "1y": NaN
        }
      },
      "SGE.L": {
        "name": "THE SAGE GROUP PLC ORD 1 4/77P",
        "sector": "Technology",
        "marketCap": 7724085248,
        "currency": "GBp",
        "changes": {
          "1d": NaN,
          "1w": NaN,
          "1mo": NaN,
          "3mo": NaN,
          "ytd": NaN,
          "1y": NaN
        }
      },
      "SMT.L": {
        "name": "SCOTTISH MORTGAGE INVESTMENT TR",
        "sector": "",
        "marketCap": 16743277568,
        "currency": "GBp",
        "changes": {
          "1d": NaN,
          "1w": NaN,
          "1mo": NaN,
          "3mo": NaN,
          "ytd": NaN,
          "1y": NaN
        }
      },
      "SSE.L": {
        "name": "SSE PLC ORD 50P",
        "sector": "Utilities",
        "marketCap": 29291018240,
        "currency": "GBp",
        "changes": {
          "1d": NaN,
          "1w": NaN,
          "1mo": NaN,
          "3mo": NaN,
          "ytd": NaN,
          "1y": NaN
        }
      },
      "SVT.L": {
        "name": "SEVERN TRENT PLC ORD 97 17/19P",
        "sector": "Utilities",
        "marketCap": 9376014336,
        "currency": "GBp",
        "changes": {
          "1d": NaN,
          "1w": NaN,
          "1mo": NaN,
          "3mo": NaN,
          "ytd": NaN,
          "1y": NaN
        }
      }
    },
    "China": {
      "600519.SS": {
        "name": "KWEICHOW MOUTAI",
        "sector": "Cons. Defensive",
        "marketCap": 1631708119040,
        "currency": "CNY",
        "changes": {
          "1d": 2.33,
          "1w": -0.61,
          "1mo": -7.14,
          "3mo": -10.45,
          "ytd": -8.63,
          "1y": -12.48
        }
      },
      "601398.SS": {
        "name": "INDUSTRIAL & COMMERCIAL BK OF C",
        "sector": "Financials",
        "marketCap": 2537612640256,
        "currency": "CNY",
        "changes": {
          "1d": -0.84,
          "1w": -0.42,
          "1mo": -3.0,
          "3mo": 5.27,
          "ytd": -6.85,
          "1y": 7.25
        }
      },
      "601288.SS": {
        "name": "AGRICULTURAL BANK OF CHINA",
        "sector": "Financials",
        "marketCap": 2208393068544,
        "currency": "CNY",
        "changes": {
          "1d": -1.71,
          "1w": -3.07,
          "1mo": -7.03,
          "3mo": 0.52,
          "ytd": -15.02,
          "1y": 20.57
        }
      },
      "601939.SS": {
        "name": "CHINA CONSTRUCTION BANK",
        "sector": "Financials",
        "marketCap": 2673556062208,
        "currency": "CNY",
        "changes": {
          "1d": -0.87,
          "1w": 1.69,
          "1mo": 5.58,
          "3mo": 18.98,
          "ytd": 10.49,
          "1y": 15.0
        }
      },
      "601628.SS": {
        "name": "CHINA LIFE INSURANCE CO LTD",
        "sector": "Financials",
        "marketCap": 945736974336,
        "currency": "CNY",
        "changes": {
          "1d": -1.01,
          "1w": -1.73,
          "1mo": -8.75,
          "3mo": -24.78,
          "ytd": -30.68,
          "1y": -11.73
        }
      },
      "600036.SS": {
        "name": "CHINA MERCHANTS BANK CO LTD",
        "sector": "Financials",
        "marketCap": 933134336000,
        "currency": "CNY",
        "changes": {
          "1d": 0.0,
          "1w": -0.4,
          "1mo": -6.04,
          "3mo": -4.52,
          "ytd": -10.37,
          "1y": -9.46
        }
      },
      "601166.SS": {
        "name": "INDUSTRIAL BANK CO LTD",
        "sector": "Financials",
        "marketCap": 380931407872,
        "currency": "CNY",
        "changes": {
          "1d": 0.95,
          "1w": 3.63,
          "1mo": -0.94,
          "3mo": -1.69,
          "ytd": -11.92,
          "1y": -14.74
        }
      },
      "600900.SS": {
        "name": "CHINA YANGTZE POWER CO",
        "sector": "Utilities",
        "marketCap": 666514227200,
        "currency": "CNY",
        "changes": {
          "1d": 0.37,
          "1w": 2.18,
          "1mo": 2.18,
          "3mo": 4.61,
          "ytd": 0.65,
          "1y": -7.0
        }
      },
      "601088.SS": {
        "name": "CHINA SHENHUA ENERGY COMPANY LT",
        "sector": "Energy",
        "marketCap": 999882883072,
        "currency": "CNY",
        "changes": {
          "1d": 2.9,
          "1w": 1.86,
          "1mo": -1.45,
          "3mo": 9.09,
          "ytd": 14.51,
          "1y": 26.28
        }
      },
      "601857.SS": {
        "name": "PETROCHINA CO",
        "sector": "Energy",
        "marketCap": 1976626577408,
        "currency": "CNY",
        "changes": {
          "1d": -1.46,
          "1w": -4.34,
          "1mo": -9.7,
          "3mo": -0.55,
          "ytd": 7.25,
          "1y": 39.54
        }
      },
      "000858.SZ": {
        "name": "WULIANGYE YIBIN CO. LTD.",
        "sector": "Cons. Defensive",
        "marketCap": 325628100608,
        "currency": "CNY",
        "changes": {
          "1d": 0.64,
          "1w": -1.71,
          "1mo": -16.28,
          "3mo": -19.38,
          "ytd": -22.25,
          "1y": -30.2
        }
      },
      "000333.SZ": {
        "name": "MIDEA GROUP CO LTD",
        "sector": "Cons. Cyclical",
        "marketCap": 609115242496,
        "currency": "CNY",
        "changes": {
          "1d": 0.6,
          "1w": -1.8,
          "1mo": 0.67,
          "3mo": 1.77,
          "ytd": 1.72,
          "1y": 7.62
        }
      },
      "002594.SZ": {
        "name": "BYD COMPANY LIMITED",
        "sector": "Cons. Cyclical",
        "marketCap": 868139532288,
        "currency": "CNY",
        "changes": {
          "1d": -1.38,
          "1w": 1.83,
          "1mo": -6.96,
          "3mo": 6.61,
          "ytd": -2.95,
          "1y": -22.38
        }
      },
      "300750.SZ": {
        "name": "CONTEMPORARY AMPEREX TECHNOLOGY",
        "sector": "Industrials",
        "marketCap": 1919076007936,
        "currency": "CNY",
        "changes": {
          "1d": 3.06,
          "1w": 0.77,
          "1mo": -4.62,
          "3mo": 23.2,
          "ytd": 11.62,
          "1y": 66.5
        }
      },
      "000725.SZ": {
        "name": "BOE TECHNOLOGY GROUP",
        "sector": "Technology",
        "marketCap": 211893534720,
        "currency": "CNY",
        "changes": {
          "1d": -0.87,
          "1w": 21.96,
          "1mo": 35.87,
          "3mo": 27.68,
          "ytd": 35.22,
          "1y": 51.25
        }
      },
      "601318.SS": {
        "name": "PING AN INSURANCE(GROUP)CO.OF C",
        "sector": "Financials",
        "marketCap": 964594106368,
        "currency": "CNY",
        "changes": {
          "1d": -1.84,
          "1w": -0.91,
          "1mo": -7.44,
          "3mo": -15.57,
          "ytd": -26.38,
          "1y": 4.36
        }
      },
      "600276.SS": {
        "name": "JIANGSU HENGRUI PHARMACEUTICALS",
        "sector": "Healthcare",
        "marketCap": 334315749376,
        "currency": "CNY",
        "changes": {
          "1d": 2.8,
          "1w": -1.7,
          "1mo": -8.68,
          "3mo": -10.58,
          "ytd": -19.82,
          "1y": -5.32
        }
      },
      "600887.SS": {
        "name": "INNER MONGOLIA YILI INDS. GP CO",
        "sector": "Cons. Defensive",
        "marketCap": 168381104128,
        "currency": "CNY",
        "changes": {
          "1d": 0.15,
          "1w": -0.52,
          "1mo": 5.43,
          "3mo": 2.07,
          "ytd": -6.96,
          "1y": -7.91
        }
      },
      "603288.SS": {
        "name": "FOSHAN HAITIAN FLAVOURING AND F",
        "sector": "Cons. Defensive",
        "marketCap": 209787928576,
        "currency": "CNY",
        "changes": {
          "1d": 0.62,
          "1w": 1.44,
          "1mo": -10.04,
          "3mo": -0.31,
          "ytd": -4.73,
          "1y": -16.67
        }
      },
      "601012.SS": {
        "name": "LONGI GREEN ENERGY TECHNOLOGY C",
        "sector": "Technology",
        "marketCap": 108821020672,
        "currency": "CNY",
        "changes": {
          "1d": -1.64,
          "1w": -2.91,
          "1mo": -16.22,
          "3mo": -21.62,
          "ytd": -22.34,
          "1y": -0.55
        }
      }
    },
    "Japan": {
      "7203.T": {
        "name": "TOYOTA MOTOR CORP",
        "sector": "Cons. Cyclical",
        "marketCap": 39204419534848,
        "currency": "JPY",
        "changes": {
          "1d": -0.46,
          "1w": 1.01,
          "1mo": -1.92,
          "3mo": -20.19,
          "ytd": -10.19,
          "1y": 17.42
        }
      },
      "6758.T": {
        "name": "SONY GROUP CORPORATION",
        "sector": "Technology",
        "marketCap": 20825914736640,
        "currency": "JPY",
        "changes": {
          "1d": -0.65,
          "1w": -0.82,
          "1mo": 10.57,
          "3mo": -2.86,
          "ytd": -13.24,
          "1y": -6.82
        }
      },
      "8306.T": {
        "name": "MITSUBISHI UFJ FINANCIAL GROUP ",
        "sector": "Financials",
        "marketCap": 34212734304256,
        "currency": "JPY",
        "changes": {
          "1d": -0.98,
          "1w": -1.17,
          "1mo": 8.72,
          "3mo": 4.06,
          "ytd": 21.38,
          "1y": 58.57
        }
      },
      "9432.T": {
        "name": "NTT INC",
        "sector": "Comm. Services",
        "marketCap": 12294966738944,
        "currency": "JPY",
        "changes": {
          "1d": 0.87,
          "1w": -1.76,
          "1mo": -0.13,
          "3mo": 0.17,
          "ytd": -3.72,
          "1y": 3.14
        }
      },
      "6861.T": {
        "name": "KEYENCE CORP",
        "sector": "Technology",
        "marketCap": 18378555129856,
        "currency": "JPY",
        "changes": {
          "1d": -1.74,
          "1w": -1.53,
          "1mo": 3.55,
          "3mo": 15.25,
          "ytd": 33.14,
          "1y": 23.35
        }
      },
      "8035.T": {
        "name": "TOKYO ELECTRON",
        "sector": "Technology",
        "marketCap": 23982902345728,
        "currency": "JPY",
        "changes": {
          "1d": 2.1,
          "1w": 7.58,
          "1mo": 11.46,
          "3mo": 20.41,
          "ytd": 43.49,
          "1y": 130.75
        }
      },
      "9984.T": {
        "name": "SOFTBANK GROUP CORP",
        "sector": "Comm. Services",
        "marketCap": 41442571452416,
        "currency": "JPY",
        "changes": {
          "1d": -7.26,
          "1w": 20.42,
          "1mo": 24.44,
          "3mo": 78.09,
          "ytd": 57.79,
          "1y": 273.83
        }
      },
      "6367.T": {
        "name": "DAIKIN INDUSTRIES",
        "sector": "Industrials",
        "marketCap": 6853957779456,
        "currency": "JPY",
        "changes": {
          "1d": 1.17,
          "1w": -1.14,
          "1mo": 8.99,
          "3mo": 18.59,
          "ytd": 16.63,
          "1y": 47.68
        }
      },
      "7974.T": {
        "name": "NINTENDO CO LTD",
        "sector": "Comm. Services",
        "marketCap": 8220823257088,
        "currency": "JPY",
        "changes": {
          "1d": 1.01,
          "1w": -1.97,
          "1mo": -9.65,
          "3mo": -19.17,
          "ytd": -31.73,
          "1y": -40.24
        }
      },
      "8316.T": {
        "name": "SUMITOMO MITSUI FINANCIAL GROUP",
        "sector": "Financials",
        "marketCap": 22713768869888,
        "currency": "JPY",
        "changes": {
          "1d": -1.9,
          "1w": -1.34,
          "1mo": 10.1,
          "3mo": 0.73,
          "ytd": 16.55,
          "1y": 69.96
        }
      },
      "4519.T": {
        "name": "CHUGAI PHARMACEUTICAL CO",
        "sector": "Healthcare",
        "marketCap": 12965321375744,
        "currency": "JPY",
        "changes": {
          "1d": 3.85,
          "1w": 0.54,
          "1mo": 5.82,
          "3mo": -24.65,
          "ytd": -7.49,
          "1y": 7.24
        }
      },
      "6501.T": {
        "name": "HITACHI",
        "sector": "Industrials",
        "marketCap": 22337128759296,
        "currency": "JPY",
        "changes": {
          "1d": -1.9,
          "1w": -3.18,
          "1mo": -7.39,
          "3mo": -4.54,
          "ytd": -1.57,
          "1y": 27.68
        }
      },
      "9433.T": {
        "name": "KDDI CORPORATION",
        "sector": "Comm. Services",
        "marketCap": 10239137021952,
        "currency": "JPY",
        "changes": {
          "1d": 2.79,
          "1w": -1.05,
          "1mo": 6.81,
          "3mo": 2.19,
          "ytd": -0.14,
          "1y": 9.82
        }
      },
      "8411.T": {
        "name": "MIZUHO FINANCIAL GROUP",
        "sector": "Financials",
        "marketCap": 17598823530496,
        "currency": "JPY",
        "changes": {
          "1d": -1.93,
          "1w": -1.15,
          "1mo": 9.38,
          "3mo": 2.08,
          "ytd": 24.28,
          "1y": 87.06
        }
      },
      "7267.T": {
        "name": "HONDA MOTOR CO",
        "sector": "Cons. Cyclical",
        "marketCap": 5533303046144,
        "currency": "JPY",
        "changes": {
          "1d": 1.03,
          "1w": 2.71,
          "1mo": 9.98,
          "3mo": -7.88,
          "ytd": -6.31,
          "1y": 5.61
        }
      },
      "6954.T": {
        "name": "FANUC CORPORATION",
        "sector": "Industrials",
        "marketCap": 7608974442496,
        "currency": "JPY",
        "changes": {
          "1d": -2.92,
          "1w": 6.35,
          "1mo": 12.38,
          "3mo": 15.76,
          "ytd": 30.62,
          "1y": 111.08
        }
      },
      "4063.T": {
        "name": "SHIN-ETSU CHEMICAL CO",
        "sector": "Materials",
        "marketCap": 13751490183168,
        "currency": "JPY",
        "changes": {
          "1d": 5.47,
          "1w": 8.01,
          "1mo": 6.58,
          "3mo": 21.12,
          "ytd": 51.1,
          "1y": 64.29
        }
      },
      "8766.T": {
        "name": "TOKIO MARINE HOLDINGS INC",
        "sector": "Financials",
        "marketCap": 14164854571008,
        "currency": "JPY",
        "changes": {
          "1d": 0.15,
          "1w": -4.29,
          "1mo": 2.83,
          "3mo": 14.59,
          "ytd": 26.53,
          "1y": 29.17
        }
      },
      "6098.T": {
        "name": "RECRUIT HOLDINGS CO LTD",
        "sector": "Comm. Services",
        "marketCap": 13787630403584,
        "currency": "JPY",
        "changes": {
          "1d": 0.84,
          "1w": 3.59,
          "1mo": 35.68,
          "3mo": 44.57,
          "ytd": 10.04,
          "1y": 15.09
        }
      },
      "7741.T": {
        "name": "HOYA CORP",
        "sector": "Healthcare",
        "marketCap": 9097121366016,
        "currency": "JPY",
        "changes": {
          "1d": 4.72,
          "1w": 2.31,
          "1mo": -6.03,
          "3mo": -3.18,
          "ytd": 13.46,
          "1y": 53.61
        }
      }
    },
    "Korea": {
      "005930.KS": {
        "name": "SamsungElec",
        "sector": "Technology",
        "marketCap": 2015934973739008,
        "currency": "KRW",
        "changes": {
          "1d": 2.68,
          "1w": 11.23,
          "1mo": 36.75,
          "3mo": 42.09,
          "ytd": 139.41,
          "1y": 479.62
        }
      },
      "000660.KS": {
        "name": "SK hynix",
        "sector": "Technology",
        "marketCap": 1592204506169344,
        "currency": "KRW",
        "changes": {
          "1d": 9.31,
          "1w": 28.54,
          "1mo": 73.61,
          "3mo": 111.4,
          "ytd": 231.93,
          "1y": 1014.11
        }
      },
      "207940.KS": {
        "name": "SAMSUNG BIOLOGICS",
        "sector": "Healthcare",
        "marketCap": 64066676588544,
        "currency": "KRW",
        "changes": {
          "1d": -2.88,
          "1w": 3.52,
          "1mo": -8.28,
          "3mo": -22.16,
          "ytd": -17.77,
          "1y": -12.27
        }
      },
      "005380.KS": {
        "name": "HyundaiMtr",
        "sector": "Cons. Cyclical",
        "marketCap": 178309006622720,
        "currency": "KRW",
        "changes": {
          "1d": -1.16,
          "1w": 15.03,
          "1mo": 29.96,
          "3mo": 1.04,
          "ytd": 129.14,
          "1y": 289.25
        }
      },
      "035420.KS": {
        "name": "NAVER",
        "sector": "Comm. Services",
        "marketCap": 29717581266944,
        "currency": "KRW",
        "changes": {
          "1d": -0.6,
          "1w": 3.81,
          "1mo": -7.53,
          "3mo": -21.89,
          "ytd": -18.67,
          "1y": 9.3
        }
      },
      "051910.KS": {
        "name": "LGCHEM",
        "sector": "Materials",
        "marketCap": 25909058863104,
        "currency": "KRW",
        "changes": {
          "1d": -5.7,
          "1w": -0.3,
          "1mo": -12.78,
          "3mo": -20.21,
          "ytd": 3.3,
          "1y": 82.14
        }
      },
      "006400.KS": {
        "name": "SAMSUNG SDI CO.,LTD.",
        "sector": "Industrials",
        "marketCap": 49576987852800,
        "currency": "KRW",
        "changes": {
          "1d": -1.87,
          "1w": 10.53,
          "1mo": -0.79,
          "3mo": 35.19,
          "ytd": 140.0,
          "1y": 293.26
        }
      },
      "035720.KS": {
        "name": "Kakao",
        "sector": "Comm. Services",
        "marketCap": 17847696752640,
        "currency": "KRW",
        "changes": {
          "1d": -2.29,
          "1w": 0.87,
          "1mo": -16.41,
          "3mo": -34.9,
          "ytd": -34.69,
          "1y": -0.96
        }
      },
      "028260.KS": {
        "name": "SAMSUNG C&T",
        "sector": "Industrials",
        "marketCap": 67172235739136,
        "currency": "KRW",
        "changes": {
          "1d": -0.12,
          "1w": 10.8,
          "1mo": 31.57,
          "3mo": 17.12,
          "ytd": 67.55,
          "1y": 175.97
        }
      },
      "012330.KS": {
        "name": "Mobis",
        "sector": "Cons. Cyclical",
        "marketCap": 61356241846272,
        "currency": "KRW",
        "changes": {
          "1d": 3.61,
          "1w": 28.6,
          "1mo": 59.08,
          "3mo": 34.64,
          "ytd": 88.64,
          "1y": 187.92
        }
      },
      "000270.KS": {
        "name": "KIA CORP.",
        "sector": "Cons. Cyclical",
        "marketCap": 64011647320064,
        "currency": "KRW",
        "changes": {
          "1d": null,
          "1w": -1.91,
          "1mo": 5.85,
          "3mo": -5.69,
          "ytd": 42.56,
          "1y": 93.18
        }
      },
      "105560.KS": {
        "name": "KBFinancialGroup",
        "sector": "Financials",
        "marketCap": 54550975217664,
        "currency": "KRW",
        "changes": {
          "1d": null,
          "1w": -1.28,
          "1mo": -2.45,
          "3mo": 0.92,
          "ytd": 26.85,
          "1y": 57.2
        }
      },
      "032830.KS": {
        "name": "SAMSUNG LIFE",
        "sector": "Financials",
        "marketCap": 63659262869504,
        "currency": "KRW",
        "changes": {
          "1d": null,
          "1w": -0.14,
          "1mo": 40.67,
          "3mo": 60.05,
          "ytd": 126.81,
          "1y": 279.74
        }
      },
      "096770.KS": {
        "name": "SK Innovation",
        "sector": "Energy",
        "marketCap": 19637636956160,
        "currency": "KRW",
        "changes": {
          "1d": null,
          "1w": -2.86,
          "1mo": -13.23,
          "3mo": -11.84,
          "ytd": 15.52,
          "1y": 32.95
        }
      },
      "003550.KS": {
        "name": "LG Corp.",
        "sector": "Technology",
        "marketCap": 18226817794048,
        "currency": "KRW",
        "changes": {
          "1d": null,
          "1w": -3.9,
          "1mo": 20.37,
          "3mo": 18.1,
          "ytd": 49.45,
          "1y": 76.2
        }
      },
      "011200.KS": {
        "name": "HMM",
        "sector": "Industrials",
        "marketCap": 18619517894656,
        "currency": "KRW",
        "changes": {
          "1d": null,
          "1w": -2.52,
          "1mo": -4.87,
          "3mo": -19.43,
          "ytd": 0.73,
          "1y": -6.23
        }
      },
      "017670.KS": {
        "name": "SKTelecom",
        "sector": "Comm. Services",
        "marketCap": 21391013314560,
        "currency": "KRW",
        "changes": {
          "1d": NaN,
          "1w": NaN,
          "1mo": NaN,
          "3mo": NaN,
          "ytd": NaN,
          "1y": NaN
        }
      },
      "030200.KS": {
        "name": "KT",
        "sector": "Comm. Services",
        "marketCap": 12803814457344,
        "currency": "KRW",
        "changes": {
          "1d": null,
          "1w": -3.09,
          "1mo": -11.36,
          "3mo": -14.32,
          "ytd": 6.17,
          "1y": 9.72
        }
      },
      "009150.KS": {
        "name": "SamsungElecMech",
        "sector": "Technology",
        "marketCap": 123142013976576,
        "currency": "KRW",
        "changes": {
          "1d": null,
          "1w": 35.38,
          "1mo": 94.28,
          "3mo": 298.53,
          "ytd": 503.7,
          "1y": 1234.08
        }
      },
      "086790.KS": {
        "name": "HANAFINANCIALGR",
        "sector": "Financials",
        "marketCap": 31764026228736,
        "currency": "KRW",
        "changes": {
          "1d": null,
          "1w": -0.84,
          "1mo": -5.94,
          "3mo": -0.53,
          "ytd": 29.31,
          "1y": 76.32
        }
      }
    },
    "HongKong": {
      "0700.HK": {
        "name": "TENCENT",
        "sector": "Comm. Services",
        "marketCap": 3923231899648,
        "currency": "HKD",
        "changes": {
          "1d": -1.05,
          "1w": -4.57,
          "1mo": -8.18,
          "3mo": -15.16,
          "ytd": -29.46,
          "1y": -14.17
        }
      },
      "0941.HK": {
        "name": "CHINA MOBILE",
        "sector": "Comm. Services",
        "marketCap": 1844120518656,
        "currency": "HKD",
        "changes": {
          "1d": -0.47,
          "1w": -1.56,
          "1mo": 0.95,
          "3mo": 7.44,
          "ytd": 2.1,
          "1y": 1.89
        }
      },
      "1299.HK": {
        "name": "AIA",
        "sector": "Financials",
        "marketCap": 877261160448,
        "currency": "HKD",
        "changes": {
          "1d": 0.3,
          "1w": 0.36,
          "1mo": 1.62,
          "3mo": -2.59,
          "ytd": 1.5,
          "1y": 33.24
        }
      },
      "0005.HK": {
        "name": "HSBC HOLDINGS",
        "sector": "Financials",
        "marketCap": 2513927143424,
        "currency": "HKD",
        "changes": {
          "1d": 0.76,
          "1w": 5.7,
          "1mo": 4.64,
          "3mo": 2.31,
          "ytd": 21.24,
          "1y": 65.54
        }
      },
      "0939.HK": {
        "name": "CCB",
        "sector": "Financials",
        "marketCap": 2244531191808,
        "currency": "HKD",
        "changes": {
          "1d": -1.72,
          "1w": -1.72,
          "1mo": -3.6,
          "3mo": 7.38,
          "ytd": 10.0,
          "1y": 25.55
        }
      },
      "2318.HK": {
        "name": "PING AN",
        "sector": "Financials",
        "marketCap": 1084647800832,
        "currency": "HKD",
        "changes": {
          "1d": -1.24,
          "1w": -2.04,
          "1mo": -1.64,
          "3mo": -11.91,
          "ytd": -10.33,
          "1y": 32.06
        }
      },
      "1398.HK": {
        "name": "ICBC",
        "sector": "Financials",
        "marketCap": 2395050082304,
        "currency": "HKD",
        "changes": {
          "1d": -0.88,
          "1w": -2.33,
          "1mo": -4.28,
          "3mo": 7.15,
          "ytd": 9.01,
          "1y": 27.95
        }
      },
      "3690.HK": {
        "name": "MEITUAN-W",
        "sector": "Cons. Cyclical",
        "marketCap": 479749537792,
        "currency": "HKD",
        "changes": {
          "1d": -1.4,
          "1w": -6.22,
          "1mo": -5.07,
          "3mo": -4.25,
          "ytd": -25.72,
          "1y": -41.18
        }
      },
      "9988.HK": {
        "name": "BABA-W",
        "sector": "Cons. Cyclical",
        "marketCap": 2385698881536,
        "currency": "HKD",
        "changes": {
          "1d": -2.59,
          "1w": -5.76,
          "1mo": -4.53,
          "3mo": -13.02,
          "ytd": -16.58,
          "1y": 5.56
        }
      },
      "0883.HK": {
        "name": "CNOOC",
        "sector": "Energy",
        "marketCap": 1250988392448,
        "currency": "HKD",
        "changes": {
          "1d": -2.23,
          "1w": -5.32,
          "1mo": -7.45,
          "3mo": 3.95,
          "ytd": 20.4,
          "1y": 58.26
        }
      },
      "2020.HK": {
        "name": "ANTA SPORTS",
        "sector": "Cons. Cyclical",
        "marketCap": 209034182656,
        "currency": "HKD",
        "changes": {
          "1d": 0.27,
          "1w": -1.95,
          "1mo": -8.09,
          "3mo": -10.03,
          "ytd": -6.57,
          "1y": -17.93
        }
      },
      "0388.HK": {
        "name": "HKEX",
        "sector": "Financials",
        "marketCap": 508393324544,
        "currency": "HKD",
        "changes": {
          "1d": -0.84,
          "1w": -2.19,
          "1mo": -2.38,
          "3mo": -2.48,
          "ytd": -1.73,
          "1y": 3.98
        }
      },
      "1810.HK": {
        "name": "XIAOMI-W",
        "sector": "Technology",
        "marketCap": 732876242944,
        "currency": "HKD",
        "changes": {
          "1d": -4.57,
          "1w": -5.77,
          "1mo": -8.68,
          "3mo": -18.62,
          "ytd": -29.49,
          "1y": -44.91
        }
      },
      "0016.HK": {
        "name": "SHK PPT",
        "sector": "Real Estate",
        "marketCap": 382796791808,
        "currency": "HKD",
        "changes": {
          "1d": -2.22,
          "1w": -3.65,
          "1mo": -3.15,
          "3mo": -8.88,
          "ytd": 37.72,
          "1y": 65.41
        }
      },
      "1177.HK": {
        "name": "SBP GROUP",
        "sector": "Healthcare",
        "marketCap": 89181962240,
        "currency": "HKD",
        "changes": {
          "1d": -1.38,
          "1w": -3.29,
          "1mo": -9.75,
          "3mo": -17.36,
          "ytd": -21.38,
          "1y": 19.27
        }
      },
      "2382.HK": {
        "name": "SUNNY OPTICAL",
        "sector": "Technology",
        "marketCap": 80724238336,
        "currency": "HKD",
        "changes": {
          "1d": 1.62,
          "1w": 19.76,
          "1mo": 12.84,
          "3mo": 29.01,
          "ytd": 10.6,
          "1y": 24.39
        }
      },
      "0011.HK": {
        "name": "0011.HK",
        "sector": "",
        "marketCap": null,
        "currency": "USD",
        "changes": {
          "1d": null,
          "1w": null,
          "1mo": null,
          "3mo": null,
          "ytd": null,
          "1y": null
        }
      },
      "2269.HK": {
        "name": "WUXI BIO",
        "sector": "Healthcare",
        "marketCap": 139218944000,
        "currency": "HKD",
        "changes": {
          "1d": -2.04,
          "1w": 1.63,
          "1mo": 1.2,
          "3mo": -16.26,
          "ytd": 3.5,
          "1y": 42.11
        }
      },
      "0960.HK": {
        "name": "LONGFOR GROUP",
        "sector": "Real Estate",
        "marketCap": 54007291904,
        "currency": "HKD",
        "changes": {
          "1d": -2.24,
          "1w": -6.2,
          "1mo": -2.6,
          "3mo": -20.21,
          "ytd": -9.17,
          "1y": -18.4
        }
      },
      "9618.HK": {
        "name": "JD-SW",
        "sector": "Cons. Cyclical",
        "marketCap": 317689888768,
        "currency": "HKD",
        "changes": {
          "1d": -1.94,
          "1w": -9.0,
          "1mo": -0.6,
          "3mo": 11.9,
          "ytd": 1.5,
          "1y": -8.95
        }
      }
    },
    "Taiwan": {
      "2330.TW": {
        "name": "TAIWAN SEMICONDUCTOR MANUFACTUR",
        "sector": "Technology",
        "marketCap": 59644449914880,
        "currency": "TWD",
        "changes": {
          "1d": 1.32,
          "1w": 3.14,
          "1mo": 1.55,
          "3mo": 16.84,
          "ytd": 45.58,
          "1y": 141.9
        }
      },
      "2454.TW": {
        "name": "MEDIATEK INC",
        "sector": "Technology",
        "marketCap": 7405951254528,
        "currency": "TWD",
        "changes": {
          "1d": 8.79,
          "1w": 30.7,
          "1mo": 90.55,
          "3mo": 144.21,
          "ytd": 221.77,
          "1y": 276.8
        }
      },
      "2317.TW": {
        "name": "HON HAI PRECISION INDUSTRY",
        "sector": "Technology",
        "marketCap": 3696506961920,
        "currency": "TWD",
        "changes": {
          "1d": 1.93,
          "1w": 6.67,
          "1mo": 15.79,
          "3mo": 10.46,
          "ytd": 13.79,
          "1y": 79.99
        }
      },
      "2308.TW": {
        "name": "DELTA ELECTRONIC",
        "sector": "Technology",
        "marketCap": 6545809604608,
        "currency": "TWD",
        "changes": {
          "1d": 7.23,
          "1w": 24.14,
          "1mo": 24.75,
          "3mo": 76.84,
          "ytd": 153.27,
          "1y": 597.91
        }
      },
      "2412.TW": {
        "name": "CHUNGHWA TELECOM",
        "sector": "Comm. Services",
        "marketCap": 1062770180096,
        "currency": "TWD",
        "changes": {
          "1d": 0.74,
          "1w": -0.36,
          "1mo": 0.0,
          "3mo": -0.72,
          "ytd": 3.79,
          "1y": 8.2
        }
      },
      "2303.TW": {
        "name": "UNITED MICRO ELECTRONICS",
        "sector": "Technology",
        "marketCap": 1800413249536,
        "currency": "TWD",
        "changes": {
          "1d": 9.96,
          "1w": 23.71,
          "1mo": 97.39,
          "3mo": 122.48,
          "ytd": 194.66,
          "1y": 232.1
        }
      },
      "2882.TW": {
        "name": "CATHAY FINANCIAL HLDG CO",
        "sector": "Financials",
        "marketCap": 1252750524416,
        "currency": "TWD",
        "changes": {
          "1d": 2.77,
          "1w": 8.51,
          "1mo": 14.63,
          "3mo": 9.63,
          "ytd": 13.56,
          "1y": 44.76
        }
      },
      "2881.TW": {
        "name": "FUBON FINANCIAL HLDG CO LTD",
        "sector": "Financials",
        "marketCap": 1503229509632,
        "currency": "TWD",
        "changes": {
          "1d": 6.28,
          "1w": 14.46,
          "1mo": 25.14,
          "3mo": 18.28,
          "ytd": 15.06,
          "1y": 47.6
        }
      },
      "2891.TW": {
        "name": "CTBC FINANCIAL HOLDINGS COMPANY",
        "sector": "Financials",
        "marketCap": 1164926779392,
        "currency": "TWD",
        "changes": {
          "1d": 2.78,
          "1w": 2.96,
          "1mo": 12.33,
          "3mo": 10.04,
          "ytd": 16.54,
          "1y": 53.13
        }
      },
      "2886.TW": {
        "name": "MEGA FINANCIAL HOLDING CO",
        "sector": "Financials",
        "marketCap": 585176776704,
        "currency": "TWD",
        "changes": {
          "1d": 0.13,
          "1w": -1.87,
          "1mo": -0.88,
          "3mo": -1.87,
          "ytd": -2.11,
          "1y": 2.44
        }
      },
      "3711.TW": {
        "name": "ASE TECHNOLOGY HOLDING CO LTD",
        "sector": "Technology",
        "marketCap": 2817026424832,
        "currency": "TWD",
        "changes": {
          "1d": 5.07,
          "1w": 25.88,
          "1mo": 29.57,
          "3mo": 73.28,
          "ytd": 148.84,
          "1y": 370.85
        }
      },
      "2002.TW": {
        "name": "CHINA STEEL CORP",
        "sector": "Materials",
        "marketCap": 291848126464,
        "currency": "TWD",
        "changes": {
          "1d": -2.05,
          "1w": 4.95,
          "1mo": 1.87,
          "3mo": -5.68,
          "ytd": 1.87,
          "1y": -2.9
        }
      },
      "1301.TW": {
        "name": "FORMOSA PLASTIC",
        "sector": "Materials",
        "marketCap": 289322926080,
        "currency": "TWD",
        "changes": {
          "1d": 1.56,
          "1w": -0.66,
          "1mo": -9.64,
          "3mo": -10.36,
          "ytd": 18.21,
          "1y": 29.85
        }
      },
      "1303.TW": {
        "name": "NAN YA PLASTIC",
        "sector": "Materials",
        "marketCap": 757393522688,
        "currency": "TWD",
        "changes": {
          "1d": 5.18,
          "1w": 9.39,
          "1mo": 8.77,
          "3mo": 6.7,
          "ytd": 67.54,
          "1y": 230.4
        }
      },
      "2207.TW": {
        "name": "HOTAI MOTOR CO",
        "sector": "Cons. Cyclical",
        "marketCap": 259888447488,
        "currency": "TWD",
        "changes": {
          "1d": 0.97,
          "1w": 0.11,
          "1mo": -4.21,
          "3mo": -18.87,
          "ytd": -14.56,
          "1y": -21.84
        }
      },
      "2395.TW": {
        "name": "ADVANTECH CO LTD",
        "sector": "Technology",
        "marketCap": 441941295104,
        "currency": "TWD",
        "changes": {
          "1d": -0.2,
          "1w": 9.82,
          "1mo": 40.22,
          "3mo": 51.26,
          "ytd": 77.66,
          "1y": 52.18
        }
      },
      "3008.TW": {
        "name": "LARGAN PRECISION CO",
        "sector": "Technology",
        "marketCap": 458447683584,
        "currency": "TWD",
        "changes": {
          "1d": -4.37,
          "1w": 1.3,
          "1mo": 34.03,
          "3mo": 45.88,
          "ytd": 38.54,
          "1y": 61.75
        }
      },
      "2357.TW": {
        "name": "ASUSTEK COMPUTER INC",
        "sector": "Technology",
        "marketCap": 520674934784,
        "currency": "TWD",
        "changes": {
          "1d": 0.29,
          "1w": 6.86,
          "1mo": 19.22,
          "3mo": 32.26,
          "ytd": 26.31,
          "1y": 21.18
        }
      },
      "2408.TW": {
        "name": "NANYA TECHNOLOGY CORPORATION",
        "sector": "Technology",
        "marketCap": 966771867648,
        "currency": "TWD",
        "changes": {
          "1d": 2.8,
          "1w": 6.48,
          "1mo": 37.75,
          "3mo": 9.47,
          "ytd": 50.72,
          "1y": 643.74
        }
      },
      "5880.TW": {
        "name": "TAIWAN COOPERATIVE FINANCIAL HL",
        "sector": "Financials",
        "marketCap": 356741283840,
        "currency": "TWD",
        "changes": {
          "1d": 0.22,
          "1w": 0.22,
          "1mo": -0.66,
          "3mo": -5.01,
          "ytd": -6.19,
          "1y": -1.62
        }
      }
    },
    "Europe": {
      "ASML.AS": {
        "name": "ASML HOLDING",
        "sector": "Technology",
        "marketCap": 530488885248,
        "currency": "EUR",
        "changes": {
          "1d": NaN,
          "1w": NaN,
          "1mo": NaN,
          "3mo": NaN,
          "ytd": NaN,
          "1y": NaN
        }
      },
      "MC.PA": {
        "name": "LVMH",
        "sector": "Cons. Cyclical",
        "marketCap": 239108669440,
        "currency": "EUR",
        "changes": {
          "1d": NaN,
          "1w": NaN,
          "1mo": NaN,
          "3mo": NaN,
          "ytd": NaN,
          "1y": NaN
        }
      },
      "ROG.SW": {
        "name": "ROG.SW",
        "sector": "",
        "marketCap": null,
        "currency": "USD",
        "changes": {
          "1d": null,
          "1w": null,
          "1mo": null,
          "3mo": null,
          "ytd": null,
          "1y": null
        }
      },
      "NESN.SW": {
        "name": "NESTLE N",
        "sector": "Cons. Defensive",
        "marketCap": 208529866752,
        "currency": "CHF",
        "changes": {
          "1d": NaN,
          "1w": NaN,
          "1mo": NaN,
          "3mo": NaN,
          "ytd": NaN,
          "1y": NaN
        }
      },
      "LVMH.PA": {
        "name": "1181948",
        "sector": "",
        "marketCap": null,
        "currency": "USD",
        "changes": {
          "1d": null,
          "1w": null,
          "1mo": null,
          "3mo": null,
          "ytd": null,
          "1y": null
        }
      },
      "SIE.DE": {
        "name": "SIEMENS AG                    N",
        "sector": "Industrials",
        "marketCap": 209029808128,
        "currency": "EUR",
        "changes": {
          "1d": NaN,
          "1w": NaN,
          "1mo": NaN,
          "3mo": NaN,
          "ytd": NaN,
          "1y": NaN
        }
      },
      "SAP.DE": {
        "name": "SAP SE                        I",
        "sector": "Technology",
        "marketCap": 175133851648,
        "currency": "EUR",
        "changes": {
          "1d": NaN,
          "1w": NaN,
          "1mo": NaN,
          "3mo": NaN,
          "ytd": NaN,
          "1y": NaN
        }
      },
      "SAN.MC": {
        "name": "BANCO SANTANDER S.A.",
        "sector": "Financials",
        "marketCap": 156330082304,
        "currency": "EUR",
        "changes": {
          "1d": NaN,
          "1w": NaN,
          "1mo": NaN,
          "3mo": NaN,
          "ytd": NaN,
          "1y": NaN
        }
      },
      "BNP.PA": {
        "name": "BNP PARIBAS ACT.A",
        "sector": "Financials",
        "marketCap": 101677744128,
        "currency": "EUR",
        "changes": {
          "1d": NaN,
          "1w": NaN,
          "1mo": NaN,
          "3mo": NaN,
          "ytd": NaN,
          "1y": NaN
        }
      },
      "AI.PA": {
        "name": "AIR LIQUIDE",
        "sector": "Materials",
        "marketCap": 105572335616,
        "currency": "EUR",
        "changes": {
          "1d": NaN,
          "1w": NaN,
          "1mo": NaN,
          "3mo": NaN,
          "ytd": NaN,
          "1y": NaN
        }
      },
      "TTE.PA": {
        "name": "TOTALENERGIES",
        "sector": "Energy",
        "marketCap": 167649722368,
        "currency": "EUR",
        "changes": {
          "1d": NaN,
          "1w": NaN,
          "1mo": NaN,
          "3mo": NaN,
          "ytd": NaN,
          "1y": NaN
        }
      },
      "OR.PA": {
        "name": "L'OREAL",
        "sector": "Cons. Defensive",
        "marketCap": 205960921088,
        "currency": "EUR",
        "changes": {
          "1d": NaN,
          "1w": NaN,
          "1mo": NaN,
          "3mo": NaN,
          "ytd": NaN,
          "1y": NaN
        }
      },
      "ABI.BR": {
        "name": "AB INBEV",
        "sector": "Cons. Defensive",
        "marketCap": 140190728192,
        "currency": "EUR",
        "changes": {
          "1d": NaN,
          "1w": NaN,
          "1mo": NaN,
          "3mo": NaN,
          "ytd": NaN,
          "1y": NaN
        }
      },
      "BAYN.DE": {
        "name": "Bayer AG                      N",
        "sector": "Healthcare",
        "marketCap": 37450002432,
        "currency": "EUR",
        "changes": {
          "1d": NaN,
          "1w": NaN,
          "1mo": NaN,
          "3mo": NaN,
          "ytd": NaN,
          "1y": NaN
        }
      },
      "DTE.DE": {
        "name": "DEUTSCHE TELEKOM AG           N",
        "sector": "Comm. Services",
        "marketCap": 141947584512,
        "currency": "EUR",
        "changes": {
          "1d": NaN,
          "1w": NaN,
          "1mo": NaN,
          "3mo": NaN,
          "ytd": NaN,
          "1y": NaN
        }
      },
      "IBE.MC": {
        "name": "ACCIONES IBERDROLA",
        "sector": "Utilities",
        "marketCap": 133028184064,
        "currency": "EUR",
        "changes": {
          "1d": NaN,
          "1w": NaN,
          "1mo": NaN,
          "3mo": NaN,
          "ytd": NaN,
          "1y": NaN
        }
      },
      "ALV.DE": {
        "name": "Allianz SE                    v",
        "sector": "Financials",
        "marketCap": 147694075904,
        "currency": "EUR",
        "changes": {
          "1d": NaN,
          "1w": NaN,
          "1mo": NaN,
          "3mo": NaN,
          "ytd": NaN,
          "1y": NaN
        }
      },
      "ADS.DE": {
        "name": "adidas AG                     N",
        "sector": "Cons. Cyclical",
        "marketCap": 29377849344,
        "currency": "EUR",
        "changes": {
          "1d": NaN,
          "1w": NaN,
          "1mo": NaN,
          "3mo": NaN,
          "ytd": NaN,
          "1y": NaN
        }
      },
      "BBVA.MC": {
        "name": "BANCO BILBAO VIZCAYA ARGENTARIA",
        "sector": "Financials",
        "marketCap": 111744917504,
        "currency": "EUR",
        "changes": {
          "1d": NaN,
          "1w": NaN,
          "1mo": NaN,
          "3mo": NaN,
          "ytd": NaN,
          "1y": NaN
        }
      },
      "BMW.DE": {
        "name": "BAYERISCHE MOTOREN WERKE AG   S",
        "sector": "Cons. Cyclical",
        "marketCap": 46761017344,
        "currency": "EUR",
        "changes": {
          "1d": NaN,
          "1w": NaN,
          "1mo": NaN,
          "3mo": NaN,
          "ytd": NaN,
          "1y": NaN
        }
      }
    },
    "Brazil": {
      "VALE3.SA": {
        "name": "VALE        ON      NM",
        "sector": "Materials",
        "marketCap": 355759915008,
        "currency": "BRL",
        "changes": {
          "1d": 0.46,
          "1w": 0.99,
          "1mo": -2.4,
          "3mo": -5.67,
          "ytd": 15.29,
          "1y": 68.83
        }
      },
      "PETR4.SA": {
        "name": "PETROBRAS   PN      N2",
        "sector": "Energy",
        "marketCap": 585070477312,
        "currency": "BRL",
        "changes": {
          "1d": -1.43,
          "1w": -4.74,
          "1mo": -9.61,
          "3mo": 10.36,
          "ytd": 41.34,
          "1y": 49.61
        }
      },
      "ITUB4.SA": {
        "name": "ITAUUNIBANCOPN      N1",
        "sector": "Financials",
        "marketCap": 444390703104,
        "currency": "BRL",
        "changes": {
          "1d": 0.65,
          "1w": 0.5,
          "1mo": -8.3,
          "3mo": -12.99,
          "ytd": 4.01,
          "1y": 19.04
        }
      },
      "BBDC4.SA": {
        "name": "BRADESCO    PN      N1",
        "sector": "Financials",
        "marketCap": 190272815104,
        "currency": "BRL",
        "changes": {
          "1d": 0.9,
          "1w": 0.56,
          "1mo": -8.68,
          "3mo": -13.32,
          "ytd": 0.82,
          "1y": 22.03
        }
      },
      "ABEV3.SA": {
        "name": "AMBEV S/A   ON",
        "sector": "Cons. Defensive",
        "marketCap": 258662449152,
        "currency": "BRL",
        "changes": {
          "1d": 0.12,
          "1w": 1.28,
          "1mo": 14.24,
          "3mo": 2.09,
          "ytd": 21.68,
          "1y": 22.35
        }
      },
      "WEGE3.SA": {
        "name": "WEG         ON      NM",
        "sector": "Industrials",
        "marketCap": 182308798464,
        "currency": "BRL",
        "changes": {
          "1d": 0.02,
          "1w": 2.31,
          "1mo": -9.84,
          "3mo": -12.38,
          "ytd": -9.75,
          "1y": 2.19
        }
      },
      "B3SA3.SA": {
        "name": "B3          ON      NM",
        "sector": "Financials",
        "marketCap": 82578735104,
        "currency": "BRL",
        "changes": {
          "1d": -2.72,
          "1w": -3.17,
          "1mo": -11.97,
          "3mo": -7.56,
          "ytd": 23.21,
          "1y": 19.66
        }
      },
      "RENT3.SA": {
        "name": "LOCALIZA    ON      NM",
        "sector": "Industrials",
        "marketCap": 46909349888,
        "currency": "BRL",
        "changes": {
          "1d": -2.01,
          "1w": -2.77,
          "1mo": -11.38,
          "3mo": -14.66,
          "ytd": -0.27,
          "1y": 5.44
        }
      },
      "SUZB3.SA": {
        "name": "SUZANO S.A. ON      NM",
        "sector": "Materials",
        "marketCap": 52025159680,
        "currency": "BRL",
        "changes": {
          "1d": 0.98,
          "1w": -0.4,
          "1mo": -7.08,
          "3mo": -27.42,
          "ytd": -18.85,
          "1y": -16.18
        }
      },
      "RDOR3.SA": {
        "name": "REDE D OR   ON      NM",
        "sector": "Healthcare",
        "marketCap": 75766546432,
        "currency": "BRL",
        "changes": {
          "1d": -1.71,
          "1w": -0.55,
          "1mo": -10.49,
          "3mo": -14.28,
          "ytd": -14.64,
          "1y": 2.03
        }
      },
      "GGBR4.SA": {
        "name": "GERDAU      PN  ED  N1",
        "sector": "Materials",
        "marketCap": 46704480256,
        "currency": "BRL",
        "changes": {
          "1d": 0.55,
          "1w": 1.02,
          "1mo": 10.45,
          "3mo": 14.58,
          "ytd": 17.26,
          "1y": 52.92
        }
      },
      "BRAP4.SA": {
        "name": "BRADESPAR   PN      N1",
        "sector": "Financials",
        "marketCap": 9154768896,
        "currency": "BRL",
        "changes": {
          "1d": 0.91,
          "1w": 0.91,
          "1mo": -2.35,
          "3mo": -6.2,
          "ytd": 15.99,
          "1y": 65.41
        }
      },
      "EQTL3.SA": {
        "name": "EQUATORIAL  ON      NM",
        "sector": "Utilities",
        "marketCap": 47804321792,
        "currency": "BRL",
        "changes": {
          "1d": -1.58,
          "1w": -0.39,
          "1mo": -12.45,
          "3mo": -9.78,
          "ytd": -0.81,
          "1y": 6.74
        }
      },
      "CMIG4.SA": {
        "name": "CEMIG       PN      N1",
        "sector": "Utilities",
        "marketCap": 31925211136,
        "currency": "BRL",
        "changes": {
          "1d": -0.36,
          "1w": -1.76,
          "1mo": -11.14,
          "3mo": -3.97,
          "ytd": 3.86,
          "1y": 13.9
        }
      },
      "CPLE6.SA": {
        "name": "CPLE6.SA",
        "sector": "",
        "marketCap": null,
        "currency": "USD",
        "changes": {
          "1d": null,
          "1w": null,
          "1mo": null,
          "3mo": null,
          "ytd": null,
          "1y": null
        }
      },
      "CSAN3.SA": {
        "name": "COSAN       ON      NM",
        "sector": "Energy",
        "marketCap": 15808887808,
        "currency": "BRL",
        "changes": {
          "1d": -6.31,
          "1w": -8.86,
          "1mo": -19.8,
          "3mo": -36.25,
          "ytd": -23.62,
          "1y": -50.8
        }
      },
      "PRIO3.SA": {
        "name": "PRIO        ON      NM",
        "sector": "Energy",
        "marketCap": 50653773824,
        "currency": "BRL",
        "changes": {
          "1d": -2.73,
          "1w": -7.38,
          "1mo": -2.13,
          "3mo": 15.58,
          "ytd": 50.81,
          "1y": 59.81
        }
      },
      "ELET3.SA": {
        "name": "ELET3.SA",
        "sector": "",
        "marketCap": null,
        "currency": "USD",
        "changes": {
          "1d": null,
          "1w": null,
          "1mo": null,
          "3mo": null,
          "ytd": null,
          "1y": null
        }
      },
      "JBSS3.SA": {
        "name": "JBSS3.SA",
        "sector": "",
        "marketCap": null,
        "currency": "USD",
        "changes": {
          "1d": null,
          "1w": null,
          "1mo": null,
          "3mo": null,
          "ytd": null,
          "1y": null
        }
      },
      "MGLU3.SA": {
        "name": "MAGAZ LUIZA ON      NM",
        "sector": "Cons. Cyclical",
        "marketCap": 5114378752,
        "currency": "BRL",
        "changes": {
          "1d": -0.75,
          "1w": -2.51,
          "1mo": -22.63,
          "3mo": -28.75,
          "ytd": -24.55,
          "1y": -25.11
        }
      }
    },
    "Turkey": {
      "GARAN.IS": {
        "name": "GARANTI BANKASI",
        "sector": "Financials",
        "marketCap": 516180017152,
        "currency": "TRY",
        "changes": {
          "1d": null,
          "1w": 2.42,
          "1mo": -10.1,
          "3mo": -20.13,
          "ytd": -14.58,
          "1y": 15.82
        }
      },
      "AKBNK.IS": {
        "name": "AKBANK",
        "sector": "Financials",
        "marketCap": 332800000000,
        "currency": "TRY",
        "changes": {
          "1d": null,
          "1w": 2.89,
          "1mo": -17.63,
          "3mo": -26.73,
          "ytd": -10.13,
          "1y": 29.64
        }
      },
      "THYAO.IS": {
        "name": "TURK HAVA YOLLARI",
        "sector": "Industrials",
        "marketCap": 407225106432,
        "currency": "TRY",
        "changes": {
          "1d": null,
          "1w": 8.3,
          "1mo": -7.41,
          "3mo": -3.5,
          "ytd": 8.2,
          "1y": 10.46
        }
      },
      "EREGL.IS": {
        "name": "EREGLI DEMIR CELIK",
        "sector": "Materials",
        "marketCap": 263363100672,
        "currency": "TRY",
        "changes": {
          "1d": null,
          "1w": 11.37,
          "1mo": 16.61,
          "3mo": 19.96,
          "ytd": 61.77,
          "1y": 66.18
        }
      },
      "BIMAS.IS": {
        "name": "BIM MAGAZALAR",
        "sector": "Cons. Defensive",
        "marketCap": 442295943168,
        "currency": "TRY",
        "changes": {
          "1d": null,
          "1w": -0.93,
          "1mo": -0.86,
          "3mo": 11.76,
          "ytd": 37.38,
          "1y": 59.35
        }
      },
      "SAHOL.IS": {
        "name": "SABANCI HOLDING",
        "sector": "Financials",
        "marketCap": 190240817152,
        "currency": "TRY",
        "changes": {
          "1d": null,
          "1w": 5.44,
          "1mo": -6.27,
          "3mo": -7.26,
          "ytd": 6.35,
          "1y": 21.64
        }
      },
      "TUPRS.IS": {
        "name": "TUPRAS",
        "sector": "Energy",
        "marketCap": 455109115904,
        "currency": "TRY",
        "changes": {
          "1d": null,
          "1w": -2.28,
          "1mo": -13.8,
          "3mo": 12.53,
          "ytd": 31.49,
          "1y": 102.78
        }
      },
      "KCHOL.IS": {
        "name": "KOC HOLDING",
        "sector": "Industrials",
        "marketCap": 479369920512,
        "currency": "TRY",
        "changes": {
          "1d": null,
          "1w": 3.16,
          "1mo": -7.76,
          "3mo": -1.72,
          "ytd": 12.23,
          "1y": 37.47
        }
      },
      "TOASO.IS": {
        "name": "TOFAS OTO. FAB.",
        "sector": "Cons. Cyclical",
        "marketCap": 147999997952,
        "currency": "TRY",
        "changes": {
          "1d": null,
          "1w": 5.62,
          "1mo": -0.34,
          "3mo": -0.5,
          "ytd": 22.28,
          "1y": 66.52
        }
      },
      "VESTL.IS": {
        "name": "VESTEL",
        "sector": "Cons. Cyclical",
        "marketCap": 8842628096,
        "currency": "TRY",
        "changes": {
          "1d": null,
          "1w": 3.13,
          "1mo": -8.6,
          "3mo": -12.66,
          "ytd": -10.4,
          "1y": -29.25
        }
      },
      "SISE.IS": {
        "name": "SISE CAM",
        "sector": "Industrials",
        "marketCap": 137053569024,
        "currency": "TRY",
        "changes": {
          "1d": null,
          "1w": 6.76,
          "1mo": -2.97,
          "3mo": 2.1,
          "ytd": 17.02,
          "1y": 34.4
        }
      },
      "HALKB.IS": {
        "name": "T. HALK BANKASI",
        "sector": "Financials",
        "marketCap": 302479147008,
        "currency": "TRY",
        "changes": {
          "1d": null,
          "1w": 20.22,
          "1mo": 5.62,
          "3mo": -14.08,
          "ytd": 9.24,
          "1y": 105.17
        }
      },
      "VAKBN.IS": {
        "name": "VAKIFLAR BANKASI",
        "sector": "Financials",
        "marketCap": 305807032320,
        "currency": "TRY",
        "changes": {
          "1d": null,
          "1w": 3.7,
          "1mo": -6.32,
          "3mo": -24.93,
          "ytd": -2.65,
          "1y": 35.86
        }
      },
      "YKBNK.IS": {
        "name": "YAPI VE KREDI BANK.",
        "sector": "Financials",
        "marketCap": 280104206336,
        "currency": "TRY",
        "changes": {
          "1d": null,
          "1w": 3.24,
          "1mo": -11.81,
          "3mo": -23.42,
          "ytd": -13.01,
          "1y": 30.24
        }
      },
      "FROTO.IS": {
        "name": "FORD OTOSAN",
        "sector": "Cons. Cyclical",
        "marketCap": 295290765312,
        "currency": "TRY",
        "changes": {
          "1d": null,
          "1w": 2.19,
          "1mo": -17.98,
          "3mo": -24.9,
          "ytd": -8.96,
          "1y": 7.66
        }
      },
      "OTKAR.IS": {
        "name": "OTOKAR",
        "sector": "Cons. Cyclical",
        "marketCap": 44280000512,
        "currency": "TRY",
        "changes": {
          "1d": null,
          "1w": 2.5,
          "1mo": -3.66,
          "3mo": -4.09,
          "ytd": -23.28,
          "1y": -5.57
        }
      },
      "PGSUS.IS": {
        "name": "PEGASUS",
        "sector": "Industrials",
        "marketCap": 85049999360,
        "currency": "TRY",
        "changes": {
          "1d": null,
          "1w": 4.42,
          "1mo": -8.55,
          "3mo": -13.44,
          "ytd": -12.77,
          "1y": -27.83
        }
      },
      "TCELL.IS": {
        "name": "TURKCELL",
        "sector": "Comm. Services",
        "marketCap": 219820703744,
        "currency": "TRY",
        "changes": {
          "1d": null,
          "1w": -4.72,
          "1mo": -13.38,
          "3mo": -12.78,
          "ytd": 5.21,
          "1y": 7.2
        }
      },
      "ARCLK.IS": {
        "name": "ARCELIK",
        "sector": "Cons. Cyclical",
        "marketCap": 68043366400,
        "currency": "TRY",
        "changes": {
          "1d": null,
          "1w": 1.67,
          "1mo": -10.99,
          "3mo": -9.98,
          "ytd": -1.14,
          "1y": -3.62
        }
      },
      "TTRAK.IS": {
        "name": "TURK TRAKTOR",
        "sector": "Industrials",
        "marketCap": 44955045888,
        "currency": "TRY",
        "changes": {
          "1d": null,
          "1w": 3.28,
          "1mo": -4.47,
          "3mo": -12.08,
          "ytd": -14.43,
          "1y": -21.87
        }
      }
    },
    "Israel": {
      "NICE": {
        "name": "NICE Ltd",
        "sector": "Technology",
        "marketCap": 5327078400,
        "currency": "USD",
        "changes": {
          "1d": -3.2,
          "1w": -2.79,
          "1mo": -10.68,
          "3mo": -21.68,
          "ytd": -18.57,
          "1y": -44.69
        }
      },
      "CHECK": {
        "name": "CHECK",
        "sector": "",
        "marketCap": null,
        "currency": "USD",
        "changes": {
          "1d": null,
          "1w": null,
          "1mo": null,
          "3mo": null,
          "ytd": null,
          "1y": null
        }
      },
      "CYBR": {
        "name": "CYBR",
        "sector": "",
        "marketCap": null,
        "currency": "USD",
        "changes": {
          "1d": null,
          "1w": null,
          "1mo": null,
          "3mo": null,
          "ytd": null,
          "1y": null
        }
      },
      "MNDY": {
        "name": "monday.com Ltd.",
        "sector": "Technology",
        "marketCap": 3939562752,
        "currency": "USD",
        "changes": {
          "1d": -0.53,
          "1w": -3.45,
          "1mo": 13.64,
          "3mo": 7.66,
          "ytd": -46.72,
          "1y": -74.29
        }
      },
      "GLBE": {
        "name": "Global-E Online Ltd.",
        "sector": "Cons. Cyclical",
        "marketCap": 4931522560,
        "currency": "USD",
        "changes": {
          "1d": -1.08,
          "1w": -2.1,
          "1mo": -8.08,
          "3mo": -15.22,
          "ytd": -22.45,
          "1y": -6.7
        }
      },
      "WIX": {
        "name": "Wix.com Ltd.",
        "sector": "Technology",
        "marketCap": 2237274880,
        "currency": "USD",
        "changes": {
          "1d": -3.38,
          "1w": -2.43,
          "1mo": -31.05,
          "3mo": -26.32,
          "ytd": -47.05,
          "1y": -64.9
        }
      },
      "TEVA": {
        "name": "Teva Pharmaceutical Industries ",
        "sector": "Healthcare",
        "marketCap": 40242597888,
        "currency": "USD",
        "changes": {
          "1d": -0.14,
          "1w": 0.7,
          "1mo": 9.3,
          "3mo": 2.34,
          "ytd": 11.66,
          "1y": 90.41
        }
      },
      "ICL": {
        "name": "ICL Group Ltd.",
        "sector": "Materials",
        "marketCap": 8557160448,
        "currency": "USD",
        "changes": {
          "1d": 0.91,
          "1w": 2.95,
          "1mo": 22.1,
          "3mo": 32.72,
          "ytd": 15.52,
          "1y": 1.4
        }
      },
      "ESLT": {
        "name": "Elbit Systems Ltd.",
        "sector": "Industrials",
        "marketCap": 38780637184,
        "currency": "USD",
        "changes": {
          "1d": -2.77,
          "1w": 7.8,
          "1mo": -0.63,
          "3mo": 0.04,
          "ytd": 40.16,
          "1y": 111.08
        }
      },
      "CEVA": {
        "name": "CEVA, Inc.",
        "sector": "Technology",
        "marketCap": 1129697408,
        "currency": "USD",
        "changes": {
          "1d": -2.97,
          "1w": 6.63,
          "1mo": 63.24,
          "3mo": 89.13,
          "ytd": 80.87,
          "1y": 110.1
        }
      },
      "SPNS": {
        "name": "SPNS",
        "sector": "",
        "marketCap": null,
        "currency": "USD",
        "changes": {
          "1d": null,
          "1w": null,
          "1mo": null,
          "3mo": null,
          "ytd": null,
          "1y": null
        }
      },
      "KLAR": {
        "name": "Klarna Group plc",
        "sector": "Technology",
        "marketCap": 6522457600,
        "currency": "USD",
        "changes": {
          "1d": 1.59,
          "1w": 7.21,
          "1mo": 24.82,
          "3mo": 30.09,
          "ytd": -39.62,
          "1y": -59.64
        }
      },
      "RADCOM": {
        "name": "RADCOM",
        "sector": "",
        "marketCap": null,
        "currency": "USD",
        "changes": {
          "1d": null,
          "1w": null,
          "1mo": null,
          "3mo": null,
          "ytd": null,
          "1y": null
        }
      },
      "GILT": {
        "name": "Gilat Satellite Networks Ltd.",
        "sector": "Technology",
        "marketCap": 1315458560,
        "currency": "USD",
        "changes": {
          "1d": -2.19,
          "1w": 11.73,
          "1mo": 5.7,
          "3mo": 0.64,
          "ytd": 29.98,
          "1y": 204.19
        }
      },
      "PERI": {
        "name": "Perion Network Ltd",
        "sector": "Comm. Services",
        "marketCap": 357269952,
        "currency": "USD",
        "changes": {
          "1d": -0.12,
          "1w": -4.0,
          "1mo": -16.67,
          "3mo": -1.03,
          "ytd": -7.49,
          "1y": -19.61
        }
      }
    },
    "Thailand": {
      "PTT.BK": {
        "name": "PTT_PTT",
        "sector": "Energy",
        "marketCap": 1033838264320,
        "currency": "THB",
        "changes": {
          "1d": 0.0,
          "1w": -2.01,
          "1mo": 3.55,
          "3mo": 2.73,
          "ytd": 19.72,
          "1y": 29.15
        }
      },
      "ADVANC.BK": {
        "name": "ADVANC_ADVANCED INFO SERVICE",
        "sector": "Comm. Services",
        "marketCap": 1046921871360,
        "currency": "THB",
        "changes": {
          "1d": -0.28,
          "1w": -1.68,
          "1mo": 1.15,
          "3mo": -7.37,
          "ytd": 17.64,
          "1y": 32.43
        }
      },
      "GULF.BK": {
        "name": "GULF_GULF DEVELOPMENT",
        "sector": "Utilities",
        "marketCap": 933739823104,
        "currency": "THB",
        "changes": {
          "1d": 1.21,
          "1w": 2.88,
          "1mo": 9.65,
          "3mo": 6.38,
          "ytd": 58.93,
          "1y": 42.61
        }
      },
      "CPALL.BK": {
        "name": "CPALL_CP ALL",
        "sector": "Cons. Defensive",
        "marketCap": 409910640640,
        "currency": "THB",
        "changes": {
          "1d": -1.6,
          "1w": -1.6,
          "1mo": 7.87,
          "3mo": -7.77,
          "ytd": 10.36,
          "1y": 0.49
        }
      },
      "AOT.BK": {
        "name": "AOT_AIRPORTS OF THAILAND",
        "sector": "Industrials",
        "marketCap": 778570629120,
        "currency": "THB",
        "changes": {
          "1d": 0.93,
          "1w": 3.32,
          "1mo": 0.93,
          "3mo": 0.0,
          "ytd": 0.0,
          "1y": 67.67
        }
      },
      "SCB.BK": {
        "name": "SCB_SCB X",
        "sector": "Financials",
        "marketCap": 456243052544,
        "currency": "THB",
        "changes": {
          "1d": 0.37,
          "1w": 1.12,
          "1mo": 3.04,
          "3mo": -2.52,
          "ytd": 1.95,
          "1y": 22.54
        }
      },
      "KBANK.BK": {
        "name": "KBANK_KASIKORNBANK",
        "sector": "Financials",
        "marketCap": 470311534592,
        "currency": "THB",
        "changes": {
          "1d": 0.25,
          "1w": 0.76,
          "1mo": 4.2,
          "3mo": 5.49,
          "ytd": 9.01,
          "1y": 33.26
        }
      },
      "BBL.BK": {
        "name": "BBL_BANGKOK BANK",
        "sector": "Financials",
        "marketCap": 332138676224,
        "currency": "THB",
        "changes": {
          "1d": 0.29,
          "1w": 2.96,
          "1mo": 8.41,
          "3mo": 2.94,
          "ytd": 6.24,
          "1y": 27.25
        }
      },
      "INTUCH.BK": {
        "name": "INTUCH.BK",
        "sector": "",
        "marketCap": null,
        "currency": "USD",
        "changes": {
          "1d": null,
          "1w": null,
          "1mo": null,
          "3mo": null,
          "ytd": null,
          "1y": null
        }
      },
      "TRUE.BK": {
        "name": "TRUE_TRUE CORPORATION",
        "sector": "Comm. Services",
        "marketCap": 469908553728,
        "currency": "THB",
        "changes": {
          "1d": -1.45,
          "1w": -3.55,
          "1mo": 2.57,
          "3mo": -4.5,
          "ytd": 22.54,
          "1y": 10.85
        }
      },
      "BDMS.BK": {
        "name": "BDMS_BANGKOK DUSIT MEDICAL",
        "sector": "Healthcare",
        "marketCap": 290823634944,
        "currency": "THB",
        "changes": {
          "1d": 0.0,
          "1w": 0.55,
          "1mo": 0.0,
          "3mo": -12.71,
          "ytd": -2.36,
          "1y": -10.81
        }
      },
      "BH.BK": {
        "name": "BH_BUMRUNGRAD HOSPITAL",
        "sector": "Healthcare",
        "marketCap": 141504053248,
        "currency": "THB",
        "changes": {
          "1d": 0.28,
          "1w": 2.59,
          "1mo": 4.09,
          "3mo": -11.94,
          "ytd": 17.96,
          "1y": 28.97
        }
      },
      "CPN.BK": {
        "name": "CPN_CENTRAL PATTANA",
        "sector": "Real Estate",
        "marketCap": 292842012672,
        "currency": "THB",
        "changes": {
          "1d": -0.76,
          "1w": -1.14,
          "1mo": 5.24,
          "3mo": -3.23,
          "ytd": 21.51,
          "1y": 47.26
        }
      },
      "HMPRO.BK": {
        "name": "HMPRO_HOME PRODUCT CENTER",
        "sector": "Cons. Cyclical",
        "marketCap": 78196252672,
        "currency": "THB",
        "changes": {
          "1d": 0.0,
          "1w": 0.0,
          "1mo": 0.0,
          "3mo": -15.31,
          "ytd": -5.04,
          "1y": -16.37
        }
      },
      "IVL.BK": {
        "name": "IVL_INDORAMA VENTURES",
        "sector": "Materials",
        "marketCap": 137556525056,
        "currency": "THB",
        "changes": {
          "1d": -0.81,
          "1w": 0.82,
          "1mo": -0.13,
          "3mo": 7.72,
          "ytd": 52.27,
          "1y": 23.17
        }
      },
      "LH.BK": {
        "name": "LH_LAND AND HOUSES",
        "sector": "Real Estate",
        "marketCap": 43735953408,
        "currency": "THB",
        "changes": {
          "1d": -0.54,
          "1w": 0.0,
          "1mo": 0.02,
          "3mo": -13.29,
          "ytd": -1.03,
          "1y": -0.5
        }
      },
      "MINT.BK": {
        "name": "MINT_MINOR INTERNATIONAL",
        "sector": "Cons. Cyclical",
        "marketCap": 124865560576,
        "currency": "THB",
        "changes": {
          "1d": -0.89,
          "1w": 0.91,
          "1mo": 4.8,
          "3mo": -12.93,
          "ytd": -7.6,
          "1y": -10.07
        }
      },
      "PSH.BK": {
        "name": "PSH_PRUKSA HOLDING",
        "sector": "Real Estate",
        "marketCap": 7530160128,
        "currency": "THB",
        "changes": {
          "1d": 0.58,
          "1w": 0.0,
          "1mo": 0.0,
          "3mo": -11.36,
          "ytd": -4.66,
          "1y": -19.07
        }
      },
      "SCC.BK": {
        "name": "SCC_THE SIAM CEMENT",
        "sector": "Industrials",
        "marketCap": 274800001024,
        "currency": "THB",
        "changes": {
          "1d": -0.87,
          "1w": 0.88,
          "1mo": 2.23,
          "3mo": 3.02,
          "ytd": 22.0,
          "1y": 39.7
        }
      },
      "TOP.BK": {
        "name": "TOP_THAI OIL",
        "sector": "Energy",
        "marketCap": 103873347584,
        "currency": "THB",
        "changes": {
          "1d": 1.64,
          "1w": -1.59,
          "1mo": 1.64,
          "3mo": -15.07,
          "ytd": 27.13,
          "1y": 64.43
        }
      }
    }
  }
}